{
  "updatedAt": "2026-07-23T20:35:46.112Z",
  "source": "binance",
  "pollMs": 5000,
  "rows": [
    {
      "symbol": "USDCUSDT",
      "base": "USDC",
      "name": "USDC",
      "price": 1.00068,
      "change24h": 0.02,
      "volume24h": 1903320722.53814,
      "marketCap": 72971956542,
      "imageUrl": "https://coin-images.coingecko.com/coins/images/6319/large/USDC.png?1769615602",
      "href": "https://www.binance.com/en/trade/USDC_USDT"
    },
    {
      "symbol": "BTCUSDT",
      "base": "BTC",
      "name": "Bitcoin",
      "price": 65136,
      "change24h": -1.179,
      "volume24h": 943156216.2273763,
      "marketCap": 1305841282653,
      "imageUrl": "https://coin-images.coingecko.com/coins/images/1/large/bitcoin.png?1696501400",
      "href": "https://www.binance.com/en/trade/BTC_USDT"
    },
    {
      "symbol": "ETHUSDT",
      "base": "ETH",
      "name": "Ethereum",
      "price": 1886.94,
      "change24h": -2.062,
      "volume24h": 431570861.811891,
      "marketCap": 227520661206,
      "imageUrl": "https://coin-images.coingecko.com/coins/images/279/large/ethereum.png?1696501628",
      "href": "https://www.binance.com/en/trade/ETH_USDT"
    },
    {
      "symbol": "KITEUSDT",
      "base": "KITE",
      "name": "Kite",
      "price": 0.1132,
      "change24h": -6.446,
      "volume24h": 199919238.28408,
      "marketCap": 270973788,
      "imageUrl": "https://coin-images.coingecko.com/coins/images/70426/large/KITE-ICON.png?1762328605",
      "href": "https://www.binance.com/en/trade/KITE_USDT"
    },
    {
      "symbol": "AEROUSDT",
      "base": "AERO",
      "name": "Aerodrome Finance",
      "price": 0.4259,
      "change24h": -2.763,
      "volume24h": 199741073.62849,
      "marketCap": 415552395,
      "imageUrl": "https://coin-images.coingecko.com/coins/images/31745/large/token.png?1696530564",
      "href": "https://www.binance.com/en/trade/AERO_USDT"
    },
    {
      "symbol": "USD1USDT",
      "base": "USD1",
      "name": "USD1",
      "price": 0.99972,
      "change24h": -0.004,
      "volume24h": 125041033.38677,
      "marketCap": 4181341932,
      "imageUrl": "https://coin-images.coingecko.com/coins/images/54977/large/USD1_1000x1000_transparent.png?1749297002",
      "href": "https://www.binance.com/en/trade/USD1_USDT"
    },
    {
      "symbol": "SOLUSDT",
      "base": "SOL",
      "name": "Solana",
      "price": 76.11,
      "change24h": -2.223,
      "volume24h": 102203732.48316,
      "marketCap": 44326646575,
      "imageUrl": "https://coin-images.coingecko.com/coins/images/4128/large/solana.png?1718769756",
      "href": "https://www.binance.com/en/trade/SOL_USDT"
    },
    {
      "symbol": "DOGEUSDT",
      "base": "DOGE",
      "name": "Dogecoin",
      "price": 0.06961,
      "change24h": -4.29,
      "volume24h": 59576336.71381,
      "marketCap": 10798432124,
      "imageUrl": "https://coin-images.coingecko.com/coins/images/5/large/dogecoin.png?1696501409",
      "href": "https://www.binance.com/en/trade/DOGE_USDT"
    },
    {
      "symbol": "XRPUSDT",
      "base": "XRP",
      "name": "XRP",
      "price": 1.1115,
      "change24h": -2.286,
      "volume24h": 57648980.58788,
      "marketCap": 69399506059,
      "imageUrl": "https://coin-images.coingecko.com/coins/images/44/large/xrp-symbol-white-128.png?1696501442",
      "href": "https://www.binance.com/en/trade/XRP_USDT"
    },
    {
      "symbol": "BANKUSDT",
      "base": "BANK",
      "name": "BANK",
      "price": 0.2477,
      "change24h": 12.642,
      "volume24h": 56374901.45731,
      "marketCap": 0,
      "imageUrl": "",
      "href": "https://www.binance.com/en/trade/BANK_USDT"
    },
    {
      "symbol": "ZECUSDT",
      "base": "ZEC",
      "name": "Zcash",
      "price": 502.58,
      "change24h": -1.878,
      "volume24h": 48533566.0094,
      "marketCap": 8431460689,
      "imageUrl": "https://coin-images.coingecko.com/coins/images/486/large/circle-zcash-color.png?1696501740",
      "href": "https://www.binance.com/en/trade/ZEC_USDT"
    },
    {
      "symbol": "DEXEUSDT",
      "base": "DEXE",
      "name": "DeXe",
      "price": 2.134,
      "change24h": -52.892,
      "volume24h": 44279600.45343,
      "marketCap": 206049640,
      "imageUrl": "https://coin-images.coingecko.com/coins/images/12713/large/DEXE_token_logo.png?1696512514",
      "href": "https://www.binance.com/en/trade/DEXE_USDT"
    },
    {
      "symbol": "BNBUSDT",
      "base": "BNB",
      "name": "BNB",
      "price": 568.25,
      "change24h": -0.407,
      "volume24h": 39161213.82335,
      "marketCap": 75640241485,
      "imageUrl": "https://coin-images.coingecko.com/coins/images/825/large/bnb-icon2_2x.png?1696501970",
      "href": "https://www.binance.com/en/trade/BNB_USDT"
    },
    {
      "symbol": "WLFIUSDT",
      "base": "WLFI",
      "name": "World Liberty Financial",
      "price": 0.0599,
      "change24h": 6.394,
      "volume24h": 31056051.82188,
      "marketCap": 1902443516,
      "imageUrl": "https://coin-images.coingecko.com/coins/images/50767/large/wlfi.png?1756438915",
      "href": "https://www.binance.com/en/trade/WLFI_USDT"
    },
    {
      "symbol": "ZAMAUSDT",
      "base": "ZAMA",
      "name": "Zama",
      "price": 0.05281,
      "change24h": 17.356,
      "volume24h": 30547052.13142,
      "marketCap": 116567826,
      "imageUrl": "https://coin-images.coingecko.com/coins/images/70921/large/zama.png?1764591992",
      "href": "https://www.binance.com/en/trade/ZAMA_USDT"
    },
    {
      "symbol": "OPNUSDT",
      "base": "OPN",
      "name": "OPN",
      "price": 0.0674,
      "change24h": -3.438,
      "volume24h": 25865307.50784,
      "marketCap": 0,
      "imageUrl": "",
      "href": "https://www.binance.com/en/trade/OPN_USDT"
    },
    {
      "symbol": "FDUSDUSDT",
      "base": "FDUSD",
      "name": "First Digital USD",
      "price": 0.9981,
      "change24h": -0.02,
      "volume24h": 24518574.0746,
      "marketCap": 346273013,
      "imageUrl": "https://coin-images.coingecko.com/coins/images/31079/large/FDUSD_icon_black.png?1731097953",
      "href": "https://www.binance.com/en/trade/FDUSD_USDT"
    },
    {
      "symbol": "RLUSDUSDT",
      "base": "RLUSD",
      "name": "Ripple USD",
      "price": 1.0008,
      "change24h": 0.03,
      "volume24h": 23887729.9506,
      "marketCap": 1591194652,
      "imageUrl": "https://coin-images.coingecko.com/coins/images/39651/large/RLUSD_200x200_%281%29.png?1727376633",
      "href": "https://www.binance.com/en/trade/RLUSD_USDT"
    },
    {
      "symbol": "EURUSDT",
      "base": "EUR",
      "name": "EUR",
      "price": 1.1384,
      "change24h": -0.272,
      "volume24h": 23345025.0225,
      "marketCap": 0,
      "imageUrl": "",
      "href": "https://www.binance.com/en/trade/EUR_USDT"
    },
    {
      "symbol": "SPCXBUSDT",
      "base": "SPCXB",
      "name": "SPCXB",
      "price": 117.44,
      "change24h": 1.119,
      "volume24h": 22876207.25004,
      "marketCap": 0,
      "imageUrl": "",
      "href": "https://www.binance.com/en/trade/SPCXB_USDT"
    },
    {
      "symbol": "TRXUSDT",
      "base": "TRX",
      "name": "TRON",
      "price": 0.3273,
      "change24h": -0.426,
      "volume24h": 21926918.04071,
      "marketCap": 31044334136,
      "imageUrl": "https://coin-images.coingecko.com/coins/images/1094/large/photo_2026-04-13_09-59-16.png?1776048311",
      "href": "https://www.binance.com/en/trade/TRX_USDT"
    },
    {
      "symbol": "SNDKBUSDT",
      "base": "SNDKB",
      "name": "SNDKB",
      "price": 1620.15,
      "change24h": -0.358,
      "volume24h": 19557556.89618,
      "marketCap": 0,
      "imageUrl": "",
      "href": "https://www.binance.com/en/trade/SNDKB_USDT"
    },
    {
      "symbol": "RIFUSDT",
      "base": "RIF",
      "name": "RIF",
      "price": 0.1084,
      "change24h": 53.759,
      "volume24h": 18429902.8289,
      "marketCap": 0,
      "imageUrl": "",
      "href": "https://www.binance.com/en/trade/RIF_USDT"
    },
    {
      "symbol": "UUSDT",
      "base": "U",
      "name": "United Stables",
      "price": 1.0006,
      "change24h": 0.03,
      "volume24h": 17902177.6943,
      "marketCap": 1060959363,
      "imageUrl": "https://coin-images.coingecko.com/coins/images/71157/large/united-stables-logo.jpg?1766061640",
      "href": "https://www.binance.com/en/trade/U_USDT"
    },
    {
      "symbol": "XAUTUSDT",
      "base": "XAUT",
      "name": "Tether Gold",
      "price": 4048.9,
      "change24h": -1.978,
      "volume24h": 17451798.360807,
      "marketCap": 2480131431,
      "imageUrl": "https://coin-images.coingecko.com/coins/images/10481/large/logo.png?1774627372",
      "href": "https://www.binance.com/en/trade/XAUT_USDT"
    },
    {
      "symbol": "ENAUSDT",
      "base": "ENA",
      "name": "Ethena",
      "price": 0.0893,
      "change24h": -2.829,
      "volume24h": 17210690.132371,
      "marketCap": 852932912,
      "imageUrl": "https://coin-images.coingecko.com/coins/images/36530/large/ethena.png?1711701436",
      "href": "https://www.binance.com/en/trade/ENA_USDT"
    },
    {
      "symbol": "REUSDT",
      "base": "RE",
      "name": "RE",
      "price": 0.541,
      "change24h": 10.544,
      "volume24h": 16870827.30025,
      "marketCap": 0,
      "imageUrl": "",
      "href": "https://www.binance.com/en/trade/RE_USDT"
    },
    {
      "symbol": "VANAUSDT",
      "base": "VANA",
      "name": "VANA",
      "price": 1.228,
      "change24h": 0.821,
      "volume24h": 15481991.3026,
      "marketCap": 0,
      "imageUrl": "",
      "href": "https://www.binance.com/en/trade/VANA_USDT"
    },
    {
      "symbol": "LTCUSDT",
      "base": "LTC",
      "name": "Litecoin",
      "price": 47.38,
      "change24h": 0.275,
      "volume24h": 14993557.86513,
      "marketCap": 3658445514,
      "imageUrl": "https://coin-images.coingecko.com/coins/images/2/large/litecoin.png?1696501400",
      "href": "https://www.binance.com/en/trade/LTC_USDT"
    },
    {
      "symbol": "WLDUSDT",
      "base": "WLD",
      "name": "Worldcoin",
      "price": 0.3887,
      "change24h": 0.206,
      "volume24h": 14725229.08155,
      "marketCap": 1376737895,
      "imageUrl": "https://coin-images.coingecko.com/coins/images/31069/large/worldcoin.jpeg?1696529903",
      "href": "https://www.binance.com/en/trade/WLD_USDT"
    },
    {
      "symbol": "SUIUSDT",
      "base": "SUI",
      "name": "Sui",
      "price": 0.7491,
      "change24h": -2.13,
      "volume24h": 14712099.54131,
      "marketCap": 3035665815,
      "imageUrl": "https://coin-images.coingecko.com/coins/images/26375/large/sui-ocean-square.png?1727791290",
      "href": "https://www.binance.com/en/trade/SUI_USDT"
    },
    {
      "symbol": "ONDOUSDT",
      "base": "ONDO",
      "name": "Ondo",
      "price": 0.4012,
      "change24h": -2.692,
      "volume24h": 13476456.19797,
      "marketCap": 1953109834,
      "imageUrl": "https://coin-images.coingecko.com/coins/images/26580/large/ONDO.png?1696525656",
      "href": "https://www.binance.com/en/trade/ONDO_USDT"
    },
    {
      "symbol": "NEARUSDT",
      "base": "NEAR",
      "name": "NEAR Protocol",
      "price": 1.887,
      "change24h": 1.071,
      "volume24h": 11795859.9402,
      "marketCap": 2454193142,
      "imageUrl": "https://coin-images.coingecko.com/coins/images/10365/large/near.jpg?1696510367",
      "href": "https://www.binance.com/en/trade/NEAR_USDT"
    },
    {
      "symbol": "SYNUSDT",
      "base": "SYN",
      "name": "SYN",
      "price": 0.14795,
      "change24h": -19.979,
      "volume24h": 11707299.9021,
      "marketCap": 0,
      "imageUrl": "",
      "href": "https://www.binance.com/en/trade/SYN_USDT"
    },
    {
      "symbol": "PAXGUSDT",
      "base": "PAXG",
      "name": "PAX Gold",
      "price": 4047.14,
      "change24h": -1.992,
      "volume24h": 11585607.292829,
      "marketCap": 1799356352,
      "imageUrl": "https://coin-images.coingecko.com/coins/images/9519/large/paxgold.png?1696509604",
      "href": "https://www.binance.com/en/trade/PAXG_USDT"
    },
    {
      "symbol": "ADAUSDT",
      "base": "ADA",
      "name": "Cardano",
      "price": 0.1704,
      "change24h": -2.405,
      "volume24h": 11400223.232,
      "marketCap": 6347694166,
      "imageUrl": "https://coin-images.coingecko.com/coins/images/975/large/cardano.png?1696502090",
      "href": "https://www.binance.com/en/trade/ADA_USDT"
    },
    {
      "symbol": "KAITOUSDT",
      "base": "KAITO",
      "name": "KAITO",
      "price": 1.0489,
      "change24h": 5.396,
      "volume24h": 11289781.18564,
      "marketCap": 252841334,
      "imageUrl": "https://coin-images.coingecko.com/coins/images/54411/large/Qm4DW488_400x400.jpg?1739552780",
      "href": "https://www.binance.com/en/trade/KAITO_USDT"
    },
    {
      "symbol": "XLMUSDT",
      "base": "XLM",
      "name": "Stellar",
      "price": 0.1836,
      "change24h": -2.028,
      "volume24h": 10620394.9443,
      "marketCap": 6270196052,
      "imageUrl": "https://coin-images.coingecko.com/coins/images/100/large/fmpFRHHQ_400x400.jpg?1735231350",
      "href": "https://www.binance.com/en/trade/XLM_USDT"
    },
    {
      "symbol": "PEPEUSDT",
      "base": "PEPE",
      "name": "Pepe",
      "price": 0.0000028,
      "change24h": -2.439,
      "volume24h": 10599172.67766329,
      "marketCap": 1174515971,
      "imageUrl": "https://coin-images.coingecko.com/coins/images/29850/large/pepe-token.jpeg?1696528776",
      "href": "https://www.binance.com/en/trade/PEPE_USDT"
    },
    {
      "symbol": "AVAXUSDT",
      "base": "AVAX",
      "name": "Avalanche",
      "price": 6.318,
      "change24h": -4.692,
      "volume24h": 10322625.81588,
      "marketCap": 2725831379,
      "imageUrl": "https://coin-images.coingecko.com/coins/images/12559/large/Avalanche_Circle_RedWhite_Trans.png?1696512369",
      "href": "https://www.binance.com/en/trade/AVAX_USDT"
    },
    {
      "symbol": "UTKUSDT",
      "base": "UTK",
      "name": "UTK",
      "price": 0.00795,
      "change24h": 16.228,
      "volume24h": 10207948.62723,
      "marketCap": 0,
      "imageUrl": "",
      "href": "https://www.binance.com/en/trade/UTK_USDT"
    },
    {
      "symbol": "UNIUSDT",
      "base": "UNI",
      "name": "Uniswap",
      "price": 3.797,
      "change24h": -0.784,
      "volume24h": 10059847.9825,
      "marketCap": 2373179989,
      "imageUrl": "https://coin-images.coingecko.com/coins/images/12504/large/uniswap-logo.png?1720676669",
      "href": "https://www.binance.com/en/trade/UNI_USDT"
    },
    {
      "symbol": "AAVEUSDT",
      "base": "AAVE",
      "name": "Aave",
      "price": 96.19,
      "change24h": -1.656,
      "volume24h": 9626866.74691,
      "marketCap": 1482046219,
      "imageUrl": "https://coin-images.coingecko.com/coins/images/12645/large/aave-token-round.png?1720472354",
      "href": "https://www.binance.com/en/trade/AAVE_USDT"
    },
    {
      "symbol": "ERAUSDT",
      "base": "ERA",
      "name": "ERA",
      "price": 0.0958,
      "change24h": -1.844,
      "volume24h": 9045274.83152,
      "marketCap": 0,
      "imageUrl": "",
      "href": "https://www.binance.com/en/trade/ERA_USDT"
    },
    {
      "symbol": "HBARUSDT",
      "base": "HBAR",
      "name": "Hedera",
      "price": 0.07224,
      "change24h": 0.866,
      "volume24h": 8647935.13494,
      "marketCap": 3170161405,
      "imageUrl": "https://coin-images.coingecko.com/coins/images/3688/large/hbar.png?1696504364",
      "href": "https://www.binance.com/en/trade/HBAR_USDT"
    },
    {
      "symbol": "TRUMPUSDT",
      "base": "TRUMP",
      "name": "Official Trump",
      "price": 1.624,
      "change24h": -0.184,
      "volume24h": 8192995.93106,
      "marketCap": 385415899,
      "imageUrl": "https://coin-images.coingecko.com/coins/images/53746/large/trump.png?1737171561",
      "href": "https://www.binance.com/en/trade/TRUMP_USDT"
    },
    {
      "symbol": "LINKUSDT",
      "base": "LINK",
      "name": "Chainlink",
      "price": 8.511,
      "change24h": -1.596,
      "volume24h": 8131624.05897,
      "marketCap": 6361888294,
      "imageUrl": "https://coin-images.coingecko.com/coins/images/877/large/Chainlink_Logo_500.png?1760023405",
      "href": "https://www.binance.com/en/trade/LINK_USDT"
    },
    {
      "symbol": "TONUSDT",
      "base": "TON",
      "name": "TON",
      "price": 1.6,
      "change24h": 0.946,
      "volume24h": 7717352.41982,
      "marketCap": 0,
      "imageUrl": "",
      "href": "https://www.binance.com/en/trade/TON_USDT"
    },
    {
      "symbol": "GRAMUSDT",
      "base": "GRAM",
      "name": "Gram (prev. Toncoin)",
      "price": 1.463,
      "change24h": -3.241,
      "volume24h": 7542631.39915,
      "marketCap": 4005586671,
      "imageUrl": "https://coin-images.coingecko.com/coins/images/17980/large/Gram_Circular_Badge.png?1781524778",
      "href": "https://www.binance.com/en/trade/GRAM_USDT"
    },
    {
      "symbol": "MUBUSDT",
      "base": "MUB",
      "name": "MUB",
      "price": 992.33,
      "change24h": 1.884,
      "volume24h": 7146461.85851,
      "marketCap": 0,
      "imageUrl": "",
      "href": "https://www.binance.com/en/trade/MUB_USDT"
    },
    {
      "symbol": "币安人生USDT",
      "base": "币安人生",
      "name": "币安人生 (BinanceLife)",
      "price": 0.6935,
      "change24h": 15.892,
      "volume24h": 7074707.08515,
      "marketCap": 693091731,
      "imageUrl": "https://coin-images.coingecko.com/coins/images/69848/large/%E5%B8%81%E5%AE%89%E4%BA%BA%E7%94%9F.png?1759839225",
      "href": "https://www.binance.com/en/trade/币安人生_USDT"
    },
    {
      "symbol": "TAOUSDT",
      "base": "TAO",
      "name": "Bittensor",
      "price": 194.4,
      "change24h": -1.069,
      "volume24h": 7005897.22545,
      "marketCap": 1865731225,
      "imageUrl": "https://coin-images.coingecko.com/coins/images/28452/large/ARUsPeNQ_400x400.jpeg?1696527447",
      "href": "https://www.binance.com/en/trade/TAO_USDT"
    },
    {
      "symbol": "TSLABUSDT",
      "base": "TSLAB",
      "name": "TSLAB",
      "price": 324,
      "change24h": -11.318,
      "volume24h": 6866818.05102,
      "marketCap": 0,
      "imageUrl": "",
      "href": "https://www.binance.com/en/trade/TSLAB_USDT"
    },
    {
      "symbol": "CRCLBUSDT",
      "base": "CRCLB",
      "name": "CRCLB",
      "price": 62.79,
      "change24h": -5.479,
      "volume24h": 6831346.3277,
      "marketCap": 0,
      "imageUrl": "",
      "href": "https://www.binance.com/en/trade/CRCLB_USDT"
    },
    {
      "symbol": "LAUSDT",
      "base": "LA",
      "name": "LA",
      "price": 0.068,
      "change24h": 23.636,
      "volume24h": 6803695.70152,
      "marketCap": 0,
      "imageUrl": "",
      "href": "https://www.binance.com/en/trade/LA_USDT"
    },
    {
      "symbol": "BARDUSDT",
      "base": "BARD",
      "name": "BARD",
      "price": 0.1272,
      "change24h": 1.76,
      "volume24h": 5492636.37771,
      "marketCap": 0,
      "imageUrl": "",
      "href": "https://www.binance.com/en/trade/BARD_USDT"
    },
    {
      "symbol": "FILUSDT",
      "base": "FIL",
      "name": "Filecoin",
      "price": 0.7316,
      "change24h": -4.341,
      "volume24h": 4999119.052975,
      "marketCap": 587351947,
      "imageUrl": "https://coin-images.coingecko.com/coins/images/12817/large/filecoin.png?1696512609",
      "href": "https://www.binance.com/en/trade/FIL_USDT"
    },
    {
      "symbol": "SOXLBUSDT",
      "base": "SOXLB",
      "name": "SOXLB",
      "price": 163,
      "change24h": -0.288,
      "volume24h": 4964961.32123,
      "marketCap": 0,
      "imageUrl": "",
      "href": "https://www.binance.com/en/trade/SOXLB_USDT"
    },
    {
      "symbol": "PUMPUSDT",
      "base": "PUMP",
      "name": "Pump.fun",
      "price": 0.00194,
      "change24h": 1.094,
      "volume24h": 4805394.078754,
      "marketCap": 772624621,
      "imageUrl": "https://coin-images.coingecko.com/coins/images/67164/large/pump.jpg?1751949376",
      "href": "https://www.binance.com/en/trade/PUMP_USDT"
    },
    {
      "symbol": "ASTERUSDT",
      "base": "ASTER",
      "name": "Aster",
      "price": 0.623,
      "change24h": -0.16,
      "volume24h": 4763093.51706,
      "marketCap": 1669916144,
      "imageUrl": "https://coin-images.coingecko.com/coins/images/69040/large/_ASTER.png?1757326782",
      "href": "https://www.binance.com/en/trade/ASTER_USDT"
    },
    {
      "symbol": "BCHUSDT",
      "base": "BCH",
      "name": "Bitcoin Cash",
      "price": 211.5,
      "change24h": -3.557,
      "volume24h": 4530851.0936,
      "marketCap": 4241914985,
      "imageUrl": "https://coin-images.coingecko.com/coins/images/780/large/bitcoin-cash-circle.png?1696501932",
      "href": "https://www.binance.com/en/trade/BCH_USDT"
    },
    {
      "symbol": "XUSDUSDT",
      "base": "XUSD",
      "name": "XUSD",
      "price": 1.001,
      "change24h": 0.01,
      "volume24h": 4354901.166,
      "marketCap": 0,
      "imageUrl": "",
      "href": "https://www.binance.com/en/trade/XUSD_USDT"
    },
    {
      "symbol": "ALLOUSDT",
      "base": "ALLO",
      "name": "Allora",
      "price": 0.5102,
      "change24h": 1.918,
      "volume24h": 4287531.76922,
      "marketCap": 122296586,
      "imageUrl": "https://coin-images.coingecko.com/coins/images/70609/large/allo-token.png?1763451165",
      "href": "https://www.binance.com/en/trade/ALLO_USDT"
    },
    {
      "symbol": "JTOUSDT",
      "base": "JTO",
      "name": "Jito",
      "price": 0.6365,
      "change24h": 1.596,
      "volume24h": 4182553.5137,
      "marketCap": 318870089,
      "imageUrl": "https://coin-images.coingecko.com/coins/images/33228/large/jto.png?1701137022",
      "href": "https://www.binance.com/en/trade/JTO_USDT"
    },
    {
      "symbol": "KORUBUSDT",
      "base": "KORUB",
      "name": "KORUB",
      "price": 22.23,
      "change24h": 3.927,
      "volume24h": 4181131.959,
      "marketCap": 0,
      "imageUrl": "",
      "href": "https://www.binance.com/en/trade/KORUB_USDT"
    },
    {
      "symbol": "ZKCUSDT",
      "base": "ZKC",
      "name": "ZKC",
      "price": 0.0444,
      "change24h": 3.738,
      "volume24h": 4125441.57073,
      "marketCap": 0,
      "imageUrl": "",
      "href": "https://www.binance.com/en/trade/ZKC_USDT"
    },
    {
      "symbol": "ARBUSDT",
      "base": "ARB",
      "name": "Arbitrum",
      "price": 0.0871,
      "change24h": -3.757,
      "volume24h": 3981589.8953,
      "marketCap": 575244969,
      "imageUrl": "https://coin-images.coingecko.com/coins/images/16547/large/arb.jpg?1721358242",
      "href": "https://www.binance.com/en/trade/ARB_USDT"
    },
    {
      "symbol": "SKHYBUSDT",
      "base": "SKHYB",
      "name": "SKHYB",
      "price": 171.3,
      "change24h": 1.331,
      "volume24h": 3962108.84598,
      "marketCap": 0,
      "imageUrl": "",
      "href": "https://www.binance.com/en/trade/SKHYB_USDT"
    },
    {
      "symbol": "DODOUSDT",
      "base": "DODO",
      "name": "DODO",
      "price": 0.01953,
      "change24h": 0.722,
      "volume24h": 3949461.097356,
      "marketCap": 0,
      "imageUrl": "",
      "href": "https://www.binance.com/en/trade/DODO_USDT"
    },
    {
      "symbol": "GOOGLBUSDT",
      "base": "GOOGLB",
      "name": "GOOGLB",
      "price": 319.69,
      "change24h": -6.812,
      "volume24h": 3886973.32139,
      "marketCap": 0,
      "imageUrl": "",
      "href": "https://www.binance.com/en/trade/GOOGLB_USDT"
    },
    {
      "symbol": "NFPUSDT",
      "base": "NFP",
      "name": "NFP",
      "price": 0.00181,
      "change24h": -66.168,
      "volume24h": 3834002.83185,
      "marketCap": 0,
      "imageUrl": "",
      "href": "https://www.binance.com/en/trade/NFP_USDT"
    },
    {
      "symbol": "VIRTUALUSDT",
      "base": "VIRTUAL",
      "name": "Virtuals Protocol",
      "price": 0.6164,
      "change24h": -2.561,
      "volume24h": 3626054.54344,
      "marketCap": 405223977,
      "imageUrl": "https://coin-images.coingecko.com/coins/images/34057/large/LOGOMARK.png?1708356054",
      "href": "https://www.binance.com/en/trade/VIRTUAL_USDT"
    },
    {
      "symbol": "PENGUUSDT",
      "base": "PENGU",
      "name": "Pudgy Penguins",
      "price": 0.006089,
      "change24h": -3.746,
      "volume24h": 3586160.079014,
      "marketCap": 382524372,
      "imageUrl": "https://coin-images.coingecko.com/coins/images/52622/large/PUDGY_PENGUINS_PENGU_PFP.png?1733809110",
      "href": "https://www.binance.com/en/trade/PENGU_USDT"
    },
    {
      "symbol": "DASHUSDT",
      "base": "DASH",
      "name": "Dash",
      "price": 33.06,
      "change24h": -1.783,
      "volume24h": 3513320.79806,
      "marketCap": 422293717,
      "imageUrl": "https://coin-images.coingecko.com/coins/images/19/large/dash-logo.png?1696501423",
      "href": "https://www.binance.com/en/trade/DASH_USDT"
    },
    {
      "symbol": "FETUSDT",
      "base": "FET",
      "name": "Artificial Superintelligence Alliance",
      "price": 0.1529,
      "change24h": -1.482,
      "volume24h": 3472519.07113,
      "marketCap": 342753679,
      "imageUrl": "https://coin-images.coingecko.com/coins/images/5681/large/ASI.png?1719827289",
      "href": "https://www.binance.com/en/trade/FET_USDT"
    },
    {
      "symbol": "DOTUSDT",
      "base": "DOT",
      "name": "Polkadot",
      "price": 0.818,
      "change24h": -2.966,
      "volume24h": 3394670.42331,
      "marketCap": 1384278294,
      "imageUrl": "https://coin-images.coingecko.com/coins/images/12171/large/polkadot.jpg?1766533446",
      "href": "https://www.binance.com/en/trade/DOT_USDT"
    },
    {
      "symbol": "TLMUSDT",
      "base": "TLM",
      "name": "TLM",
      "price": 0.001801,
      "change24h": 1.694,
      "volume24h": 3375321.692041,
      "marketCap": 0,
      "imageUrl": "",
      "href": "https://www.binance.com/en/trade/TLM_USDT"
    },
    {
      "symbol": "MIRAUSDT",
      "base": "MIRA",
      "name": "MIRA",
      "price": 0.0463,
      "change24h": -7.028,
      "volume24h": 3307641.94752,
      "marketCap": 0,
      "imageUrl": "",
      "href": "https://www.binance.com/en/trade/MIRA_USDT"
    },
    {
      "symbol": "INJUSDT",
      "base": "INJ",
      "name": "Injective",
      "price": 5.181,
      "change24h": -0.193,
      "volume24h": 3289489.23931,
      "marketCap": 517481766,
      "imageUrl": "https://coin-images.coingecko.com/coins/images/12882/large/Other_200x200.png?1738782212",
      "href": "https://www.binance.com/en/trade/INJ_USDT"
    },
    {
      "symbol": "NIGHTUSDT",
      "base": "NIGHT",
      "name": "Midnight",
      "price": 0.02143,
      "change24h": 3.377,
      "volume24h": 3288494.07301,
      "marketCap": 356037062,
      "imageUrl": "https://coin-images.coingecko.com/coins/images/71015/large/midnight.png?1765193080",
      "href": "https://www.binance.com/en/trade/NIGHT_USDT"
    },
    {
      "symbol": "XPLUSDT",
      "base": "XPL",
      "name": "Plasma",
      "price": 0.08325,
      "change24h": -1.117,
      "volume24h": 3251147.249751,
      "marketCap": 216321099,
      "imageUrl": "https://coin-images.coingecko.com/coins/images/66489/large/Plasma-symbol-green-1.png?1755142558",
      "href": "https://www.binance.com/en/trade/XPL_USDT"
    },
    {
      "symbol": "KGSTUSDT",
      "base": "KGST",
      "name": "KGST",
      "price": 0.011445,
      "change24h": -0.009,
      "volume24h": 3162790.705553,
      "marketCap": 0,
      "imageUrl": "",
      "href": "https://www.binance.com/en/trade/KGST_USDT"
    },
    {
      "symbol": "HOMEUSDT",
      "base": "HOME",
      "name": "HOME",
      "price": 0.00613,
      "change24h": -3.312,
      "volume24h": 3047532.19619,
      "marketCap": 0,
      "imageUrl": "",
      "href": "https://www.binance.com/en/trade/HOME_USDT"
    },
    {
      "symbol": "LRCUSDT",
      "base": "LRC",
      "name": "LRC",
      "price": 0.01879,
      "change24h": -6.238,
      "volume24h": 2891184.21049,
      "marketCap": 0,
      "imageUrl": "",
      "href": "https://www.binance.com/en/trade/LRC_USDT"
    },
    {
      "symbol": "APTUSDT",
      "base": "APT",
      "name": "Aptos",
      "price": 0.616,
      "change24h": -2.067,
      "volume24h": 2868584.12954,
      "marketCap": 519465575,
      "imageUrl": "https://coin-images.coingecko.com/coins/images/26455/large/Aptos-Network-Symbol-Black-RGB-1x.png?1761789140",
      "href": "https://www.binance.com/en/trade/APT_USDT"
    },
    {
      "symbol": "EPICUSDT",
      "base": "EPIC",
      "name": "EPIC",
      "price": 0.6447,
      "change24h": 6.915,
      "volume24h": 2822317.7726,
      "marketCap": 0,
      "imageUrl": "",
      "href": "https://www.binance.com/en/trade/EPIC_USDT"
    },
    {
      "symbol": "LDOUSDT",
      "base": "LDO",
      "name": "Lido DAO",
      "price": 0.3907,
      "change24h": -2.227,
      "volume24h": 2761433.691809,
      "marketCap": 326365634,
      "imageUrl": "https://coin-images.coingecko.com/coins/images/13573/large/Lido_DAO.png?1696513326",
      "href": "https://www.binance.com/en/trade/LDO_USDT"
    },
    {
      "symbol": "POLUSDT",
      "base": "POL",
      "name": "POL (ex-MATIC)",
      "price": 0.0768,
      "change24h": -2.736,
      "volume24h": 2748760.876174,
      "marketCap": 820706173,
      "imageUrl": "https://coin-images.coingecko.com/coins/images/32440/large/pol.png?1759114181",
      "href": "https://www.binance.com/en/trade/POL_USDT"
    },
    {
      "symbol": "PROMUSDT",
      "base": "PROM",
      "name": "PROM",
      "price": 1.823,
      "change24h": 20.569,
      "volume24h": 2685024.26276,
      "marketCap": 0,
      "imageUrl": "",
      "href": "https://www.binance.com/en/trade/PROM_USDT"
    },
    {
      "symbol": "ACEUSDT",
      "base": "ACE",
      "name": "ACE",
      "price": 0.0816,
      "change24h": -11.688,
      "volume24h": 2508205.14605,
      "marketCap": 0,
      "imageUrl": "",
      "href": "https://www.binance.com/en/trade/ACE_USDT"
    },
    {
      "symbol": "ZILUSDT",
      "base": "ZIL",
      "name": "ZIL",
      "price": 0.002453,
      "change24h": -0.041,
      "volume24h": 2436898.8257819,
      "marketCap": 0,
      "imageUrl": "",
      "href": "https://www.binance.com/en/trade/ZIL_USDT"
    },
    {
      "symbol": "JSTUSDT",
      "base": "JST",
      "name": "JUST",
      "price": 0.10082,
      "change24h": -0.885,
      "volume24h": 2427956.383925,
      "marketCap": 824783696,
      "imageUrl": "https://coin-images.coingecko.com/coins/images/11095/large/JUST.jpg?1696511035",
      "href": "https://www.binance.com/en/trade/JST_USDT"
    },
    {
      "symbol": "HEMIUSDT",
      "base": "HEMI",
      "name": "HEMI",
      "price": 0.00483,
      "change24h": -3.976,
      "volume24h": 2393719.787264,
      "marketCap": 0,
      "imageUrl": "",
      "href": "https://www.binance.com/en/trade/HEMI_USDT"
    },
    {
      "symbol": "INTCBUSDT",
      "base": "INTCB",
      "name": "INTCB",
      "price": 109.67,
      "change24h": 5.941,
      "volume24h": 2350076.41723,
      "marketCap": 0,
      "imageUrl": "",
      "href": "https://www.binance.com/en/trade/INTCB_USDT"
    },
    {
      "symbol": "SHIBUSDT",
      "base": "SHIB",
      "name": "Shiba Inu",
      "price": 0.00000415,
      "change24h": -2.353,
      "volume24h": 2331483.34132756,
      "marketCap": 2440204457,
      "imageUrl": "https://coin-images.coingecko.com/coins/images/11939/large/shiba.png?1696511800",
      "href": "https://www.binance.com/en/trade/SHIB_USDT"
    },
    {
      "symbol": "EIGENUSDT",
      "base": "EIGEN",
      "name": "EigenCloud (prev. EigenLayer)",
      "price": 0.2267,
      "change24h": -4.427,
      "volume24h": 2293534.238075,
      "marketCap": 167824406,
      "imageUrl": "https://coin-images.coingecko.com/coins/images/37441/large/eigencloud.jpg?1751003565",
      "href": "https://www.binance.com/en/trade/EIGEN_USDT"
    },
    {
      "symbol": "NOMUSDT",
      "base": "NOM",
      "name": "NOM",
      "price": 0.0016,
      "change24h": 3.226,
      "volume24h": 2263819.94017,
      "marketCap": 0,
      "imageUrl": "",
      "href": "https://www.binance.com/en/trade/NOM_USDT"
    },
    {
      "symbol": "ETHFIUSDT",
      "base": "ETHFI",
      "name": "Ether.fi",
      "price": 0.452,
      "change24h": -1.825,
      "volume24h": 2173058.29165,
      "marketCap": 439995964,
      "imageUrl": "https://coin-images.coingecko.com/coins/images/35958/large/etherfi.jpeg?1710254562",
      "href": "https://www.binance.com/en/trade/ETHFI_USDT"
    },
    {
      "symbol": "MORPHOUSDT",
      "base": "MORPHO",
      "name": "Morpho",
      "price": 1.985,
      "change24h": 1.952,
      "volume24h": 2172282.10117,
      "marketCap": 1299816477,
      "imageUrl": "https://coin-images.coingecko.com/coins/images/29837/large/Morpho-token-icon.png?1726771230",
      "href": "https://www.binance.com/en/trade/MORPHO_USDT"
    },
    {
      "symbol": "ICPUSDT",
      "base": "ICP",
      "name": "Internet Computer",
      "price": 2.169,
      "change24h": -2.033,
      "volume24h": 2148458.76961,
      "marketCap": 1202839228,
      "imageUrl": "https://coin-images.coingecko.com/coins/images/14495/large/Internet_Computer_logo.png?1696514180",
      "href": "https://www.binance.com/en/trade/ICP_USDT"
    }
  ]
}
