{
  "updatedAt": "2026-07-23T14:57:54.372Z",
  "source": "binance",
  "pollMs": 5000,
  "rows": [
    {
      "symbol": "USDCUSDT",
      "base": "USDC",
      "name": "USDC",
      "price": 1.00057,
      "change24h": 0.006,
      "volume24h": 2150984213.87954,
      "marketCap": 0,
      "imageUrl": "",
      "href": "https://www.binance.com/en/trade/USDC_USDT"
    },
    {
      "symbol": "BTCUSDT",
      "base": "BTC",
      "name": "BTC",
      "price": 64876,
      "change24h": -1.278,
      "volume24h": 852776975.5708554,
      "marketCap": 0,
      "imageUrl": "",
      "href": "https://www.binance.com/en/trade/BTC_USDT"
    },
    {
      "symbol": "ETHUSDT",
      "base": "ETH",
      "name": "ETH",
      "price": 1894.83,
      "change24h": -1.817,
      "volume24h": 421477330.361274,
      "marketCap": 0,
      "imageUrl": "",
      "href": "https://www.binance.com/en/trade/ETH_USDT"
    },
    {
      "symbol": "AEROUSDT",
      "base": "AERO",
      "name": "AERO",
      "price": 0.4208,
      "change24h": -2.795,
      "volume24h": 238039035.00946,
      "marketCap": 0,
      "imageUrl": "",
      "href": "https://www.binance.com/en/trade/AERO_USDT"
    },
    {
      "symbol": "KITEUSDT",
      "base": "KITE",
      "name": "KITE",
      "price": 0.1126,
      "change24h": -6.478,
      "volume24h": 210894104.9851,
      "marketCap": 0,
      "imageUrl": "",
      "href": "https://www.binance.com/en/trade/KITE_USDT"
    },
    {
      "symbol": "SOLUSDT",
      "base": "SOL",
      "name": "SOL",
      "price": 76.42,
      "change24h": -1.761,
      "volume24h": 107883543.04949,
      "marketCap": 0,
      "imageUrl": "",
      "href": "https://www.binance.com/en/trade/SOL_USDT"
    },
    {
      "symbol": "USD1USDT",
      "base": "USD1",
      "name": "USD1",
      "price": 0.99968,
      "change24h": -0.002,
      "volume24h": 105260944.2961,
      "marketCap": 0,
      "imageUrl": "",
      "href": "https://www.binance.com/en/trade/USD1_USDT"
    },
    {
      "symbol": "BANKUSDT",
      "base": "BANK",
      "name": "BANK",
      "price": 0.2552,
      "change24h": 41.072,
      "volume24h": 67414190.49933,
      "marketCap": 0,
      "imageUrl": "",
      "href": "https://www.binance.com/en/trade/BANK_USDT"
    },
    {
      "symbol": "XRPUSDT",
      "base": "XRP",
      "name": "XRP",
      "price": 1.1093,
      "change24h": -2.753,
      "volume24h": 56108891.60616,
      "marketCap": 0,
      "imageUrl": "",
      "href": "https://www.binance.com/en/trade/XRP_USDT"
    },
    {
      "symbol": "ZECUSDT",
      "base": "ZEC",
      "name": "ZEC",
      "price": 514.33,
      "change24h": 0.74,
      "volume24h": 54143138.71127,
      "marketCap": 0,
      "imageUrl": "",
      "href": "https://www.binance.com/en/trade/ZEC_USDT"
    },
    {
      "symbol": "BNBUSDT",
      "base": "BNB",
      "name": "BNB",
      "price": 566.61,
      "change24h": -0.673,
      "volume24h": 47593944.44591,
      "marketCap": 0,
      "imageUrl": "",
      "href": "https://www.binance.com/en/trade/BNB_USDT"
    },
    {
      "symbol": "DOGEUSDT",
      "base": "DOGE",
      "name": "DOGE",
      "price": 0.07019,
      "change24h": -3.519,
      "volume24h": 45271403.20554,
      "marketCap": 0,
      "imageUrl": "",
      "href": "https://www.binance.com/en/trade/DOGE_USDT"
    },
    {
      "symbol": "DEXEUSDT",
      "base": "DEXE",
      "name": "DEXE",
      "price": 3.062,
      "change24h": -36.195,
      "volume24h": 32305391.68137,
      "marketCap": 0,
      "imageUrl": "",
      "href": "https://www.binance.com/en/trade/DEXE_USDT"
    },
    {
      "symbol": "WLFIUSDT",
      "base": "WLFI",
      "name": "WLFI",
      "price": 0.061,
      "change24h": 7.584,
      "volume24h": 31502852.88656,
      "marketCap": 0,
      "imageUrl": "",
      "href": "https://www.binance.com/en/trade/WLFI_USDT"
    },
    {
      "symbol": "RLUSDUSDT",
      "base": "RLUSD",
      "name": "RLUSD",
      "price": 1.0007,
      "change24h": -0.01,
      "volume24h": 31193126.1157,
      "marketCap": 0,
      "imageUrl": "",
      "href": "https://www.binance.com/en/trade/RLUSD_USDT"
    },
    {
      "symbol": "SPCXBUSDT",
      "base": "SPCXB",
      "name": "SPCXB",
      "price": 112.05,
      "change24h": -9.146,
      "volume24h": 27002135.66936,
      "marketCap": 0,
      "imageUrl": "",
      "href": "https://www.binance.com/en/trade/SPCXB_USDT"
    },
    {
      "symbol": "ZAMAUSDT",
      "base": "ZAMA",
      "name": "ZAMA",
      "price": 0.05293,
      "change24h": 25.486,
      "volume24h": 24962289.45742,
      "marketCap": 0,
      "imageUrl": "",
      "href": "https://www.binance.com/en/trade/ZAMA_USDT"
    },
    {
      "symbol": "OPNUSDT",
      "base": "OPN",
      "name": "OPN",
      "price": 0.0686,
      "change24h": 1.932,
      "volume24h": 24335829.57885,
      "marketCap": 0,
      "imageUrl": "",
      "href": "https://www.binance.com/en/trade/OPN_USDT"
    },
    {
      "symbol": "FDUSDUSDT",
      "base": "FDUSD",
      "name": "FDUSD",
      "price": 0.9981,
      "change24h": -0.02,
      "volume24h": 23198166.1573,
      "marketCap": 0,
      "imageUrl": "",
      "href": "https://www.binance.com/en/trade/FDUSD_USDT"
    },
    {
      "symbol": "TRXUSDT",
      "base": "TRX",
      "name": "TRX",
      "price": 0.3266,
      "change24h": -0.548,
      "volume24h": 20802552.84205,
      "marketCap": 0,
      "imageUrl": "",
      "href": "https://www.binance.com/en/trade/TRX_USDT"
    },
    {
      "symbol": "REUSDT",
      "base": "RE",
      "name": "RE",
      "price": 0.4809,
      "change24h": 0.481,
      "volume24h": 20035698.43224,
      "marketCap": 0,
      "imageUrl": "",
      "href": "https://www.binance.com/en/trade/RE_USDT"
    },
    {
      "symbol": "SNDKBUSDT",
      "base": "SNDKB",
      "name": "SNDKB",
      "price": 1637.5,
      "change24h": 3.18,
      "volume24h": 19982519.690534,
      "marketCap": 0,
      "imageUrl": "",
      "href": "https://www.binance.com/en/trade/SNDKB_USDT"
    },
    {
      "symbol": "ENAUSDT",
      "base": "ENA",
      "name": "ENA",
      "price": 0.089,
      "change24h": 0.907,
      "volume24h": 19311859.896577,
      "marketCap": 0,
      "imageUrl": "",
      "href": "https://www.binance.com/en/trade/ENA_USDT"
    },
    {
      "symbol": "XAUTUSDT",
      "base": "XAUT",
      "name": "XAUT",
      "price": 4057.11,
      "change24h": -1.983,
      "volume24h": 18169942.065653,
      "marketCap": 0,
      "imageUrl": "",
      "href": "https://www.binance.com/en/trade/XAUT_USDT"
    },
    {
      "symbol": "WLDUSDT",
      "base": "WLD",
      "name": "WLD",
      "price": 0.3744,
      "change24h": -1.887,
      "volume24h": 18003149.48777,
      "marketCap": 0,
      "imageUrl": "",
      "href": "https://www.binance.com/en/trade/WLD_USDT"
    },
    {
      "symbol": "EURUSDT",
      "base": "EUR",
      "name": "EUR",
      "price": 1.1374,
      "change24h": -0.35,
      "volume24h": 16408957.00422,
      "marketCap": 0,
      "imageUrl": "",
      "href": "https://www.binance.com/en/trade/EUR_USDT"
    },
    {
      "symbol": "SUIUSDT",
      "base": "SUI",
      "name": "SUI",
      "price": 0.7501,
      "change24h": -2.407,
      "volume24h": 15896367.25663,
      "marketCap": 0,
      "imageUrl": "",
      "href": "https://www.binance.com/en/trade/SUI_USDT"
    },
    {
      "symbol": "UUSDT",
      "base": "U",
      "name": "U",
      "price": 1.0003,
      "change24h": -0.01,
      "volume24h": 15168039.7671,
      "marketCap": 0,
      "imageUrl": "",
      "href": "https://www.binance.com/en/trade/U_USDT"
    },
    {
      "symbol": "VANAUSDT",
      "base": "VANA",
      "name": "VANA",
      "price": 1.226,
      "change24h": 1.827,
      "volume24h": 14943658.79569,
      "marketCap": 0,
      "imageUrl": "",
      "href": "https://www.binance.com/en/trade/VANA_USDT"
    },
    {
      "symbol": "ONDOUSDT",
      "base": "ONDO",
      "name": "ONDO",
      "price": 0.4015,
      "change24h": -2.69,
      "volume24h": 14845020.05516,
      "marketCap": 0,
      "imageUrl": "",
      "href": "https://www.binance.com/en/trade/ONDO_USDT"
    },
    {
      "symbol": "NEARUSDT",
      "base": "NEAR",
      "name": "NEAR",
      "price": 1.882,
      "change24h": -0.265,
      "volume24h": 14690640.8031,
      "marketCap": 0,
      "imageUrl": "",
      "href": "https://www.binance.com/en/trade/NEAR_USDT"
    },
    {
      "symbol": "PAXGUSDT",
      "base": "PAXG",
      "name": "PAXG",
      "price": 4055.6,
      "change24h": -2.027,
      "volume24h": 14320084.213709,
      "marketCap": 0,
      "imageUrl": "",
      "href": "https://www.binance.com/en/trade/PAXG_USDT"
    },
    {
      "symbol": "ADAUSDT",
      "base": "ADA",
      "name": "ADA",
      "price": 0.1696,
      "change24h": -3.086,
      "volume24h": 13927010.39973,
      "marketCap": 0,
      "imageUrl": "",
      "href": "https://www.binance.com/en/trade/ADA_USDT"
    },
    {
      "symbol": "AAVEUSDT",
      "base": "AAVE",
      "name": "AAVE",
      "price": 95.92,
      "change24h": -1.215,
      "volume24h": 13598619.61428,
      "marketCap": 0,
      "imageUrl": "",
      "href": "https://www.binance.com/en/trade/AAVE_USDT"
    },
    {
      "symbol": "LTCUSDT",
      "base": "LTC",
      "name": "LTC",
      "price": 46.54,
      "change24h": -0.449,
      "volume24h": 12541323.27435,
      "marketCap": 0,
      "imageUrl": "",
      "href": "https://www.binance.com/en/trade/LTC_USDT"
    },
    {
      "symbol": "PEPEUSDT",
      "base": "PEPE",
      "name": "PEPE",
      "price": 0.0000028,
      "change24h": -1.408,
      "volume24h": 11840324.96481802,
      "marketCap": 0,
      "imageUrl": "",
      "href": "https://www.binance.com/en/trade/PEPE_USDT"
    },
    {
      "symbol": "SYNUSDT",
      "base": "SYN",
      "name": "SYN",
      "price": 0.1577,
      "change24h": -16.402,
      "volume24h": 11210554.033365,
      "marketCap": 0,
      "imageUrl": "",
      "href": "https://www.binance.com/en/trade/SYN_USDT"
    },
    {
      "symbol": "HBARUSDT",
      "base": "HBAR",
      "name": "HBAR",
      "price": 0.07143,
      "change24h": -0.833,
      "volume24h": 11036867.21858,
      "marketCap": 0,
      "imageUrl": "",
      "href": "https://www.binance.com/en/trade/HBAR_USDT"
    },
    {
      "symbol": "UNIUSDT",
      "base": "UNI",
      "name": "UNI",
      "price": 3.769,
      "change24h": 0.453,
      "volume24h": 11003978.36126,
      "marketCap": 0,
      "imageUrl": "",
      "href": "https://www.binance.com/en/trade/UNI_USDT"
    },
    {
      "symbol": "XLMUSDT",
      "base": "XLM",
      "name": "XLM",
      "price": 0.1817,
      "change24h": -3.761,
      "volume24h": 10895419.647,
      "marketCap": 0,
      "imageUrl": "",
      "href": "https://www.binance.com/en/trade/XLM_USDT"
    },
    {
      "symbol": "UTKUSDT",
      "base": "UTK",
      "name": "UTK",
      "price": 0.00795,
      "change24h": 16.228,
      "volume24h": 10207948.62723,
      "marketCap": 0,
      "imageUrl": "",
      "href": "https://www.binance.com/en/trade/UTK_USDT"
    },
    {
      "symbol": "KAITOUSDT",
      "base": "KAITO",
      "name": "KAITO",
      "price": 1.0905,
      "change24h": 9.963,
      "volume24h": 9944124.00917,
      "marketCap": 0,
      "imageUrl": "",
      "href": "https://www.binance.com/en/trade/KAITO_USDT"
    },
    {
      "symbol": "ERAUSDT",
      "base": "ERA",
      "name": "ERA",
      "price": 0.0972,
      "change24h": -5.631,
      "volume24h": 9884751.60553,
      "marketCap": 0,
      "imageUrl": "",
      "href": "https://www.binance.com/en/trade/ERA_USDT"
    },
    {
      "symbol": "RIFUSDT",
      "base": "RIF",
      "name": "RIF",
      "price": 0.1003,
      "change24h": 70.578,
      "volume24h": 9331583.2329,
      "marketCap": 0,
      "imageUrl": "",
      "href": "https://www.binance.com/en/trade/RIF_USDT"
    },
    {
      "symbol": "MIRAUSDT",
      "base": "MIRA",
      "name": "MIRA",
      "price": 0.0463,
      "change24h": 2.889,
      "volume24h": 9303785.09541,
      "marketCap": 0,
      "imageUrl": "",
      "href": "https://www.binance.com/en/trade/MIRA_USDT"
    },
    {
      "symbol": "TAOUSDT",
      "base": "TAO",
      "name": "TAO",
      "price": 194.1,
      "change24h": -2.413,
      "volume24h": 9296527.55313,
      "marketCap": 0,
      "imageUrl": "",
      "href": "https://www.binance.com/en/trade/TAO_USDT"
    },
    {
      "symbol": "LINKUSDT",
      "base": "LINK",
      "name": "LINK",
      "price": 8.473,
      "change24h": -2.001,
      "volume24h": 9084394.57467,
      "marketCap": 0,
      "imageUrl": "",
      "href": "https://www.binance.com/en/trade/LINK_USDT"
    },
    {
      "symbol": "TRUMPUSDT",
      "base": "TRUMP",
      "name": "TRUMP",
      "price": 1.642,
      "change24h": 2.753,
      "volume24h": 8875265.764851,
      "marketCap": 0,
      "imageUrl": "",
      "href": "https://www.binance.com/en/trade/TRUMP_USDT"
    },
    {
      "symbol": "GRAMUSDT",
      "base": "GRAM",
      "name": "GRAM",
      "price": 1.485,
      "change24h": -2.238,
      "volume24h": 8106819.0568,
      "marketCap": 0,
      "imageUrl": "",
      "href": "https://www.binance.com/en/trade/GRAM_USDT"
    },
    {
      "symbol": "TONUSDT",
      "base": "TON",
      "name": "TON",
      "price": 1.6,
      "change24h": 0.946,
      "volume24h": 7717352.41982,
      "marketCap": 0,
      "imageUrl": "",
      "href": "https://www.binance.com/en/trade/TON_USDT"
    },
    {
      "symbol": "MUBUSDT",
      "base": "MUB",
      "name": "MUB",
      "price": 991.61,
      "change24h": 2.408,
      "volume24h": 7303344.47315,
      "marketCap": 0,
      "imageUrl": "",
      "href": "https://www.binance.com/en/trade/MUB_USDT"
    },
    {
      "symbol": "AVAXUSDT",
      "base": "AVAX",
      "name": "AVAX",
      "price": 6.451,
      "change24h": -1.736,
      "volume24h": 6827631.75125,
      "marketCap": 0,
      "imageUrl": "",
      "href": "https://www.binance.com/en/trade/AVAX_USDT"
    },
    {
      "symbol": "PUMPUSDT",
      "base": "PUMP",
      "name": "PUMP",
      "price": 0.001933,
      "change24h": -1.226,
      "volume24h": 6087899.325179,
      "marketCap": 0,
      "imageUrl": "",
      "href": "https://www.binance.com/en/trade/PUMP_USDT"
    },
    {
      "symbol": "LISTAUSDT",
      "base": "LISTA",
      "name": "LISTA",
      "price": 0.0501,
      "change24h": -2.148,
      "volume24h": 5625422.98444,
      "marketCap": 0,
      "imageUrl": "",
      "href": "https://www.binance.com/en/trade/LISTA_USDT"
    },
    {
      "symbol": "币安人生USDT",
      "base": "币安人生",
      "name": "币安人生",
      "price": 0.6822,
      "change24h": 14.829,
      "volume24h": 5444693.28543,
      "marketCap": 0,
      "imageUrl": "",
      "href": "https://www.binance.com/en/trade/币安人生_USDT"
    },
    {
      "symbol": "CRCLBUSDT",
      "base": "CRCLB",
      "name": "CRCLB",
      "price": 62.2,
      "change24h": -8.381,
      "volume24h": 5365906.4547,
      "marketCap": 0,
      "imageUrl": "",
      "href": "https://www.binance.com/en/trade/CRCLB_USDT"
    },
    {
      "symbol": "TSLABUSDT",
      "base": "TSLAB",
      "name": "TSLAB",
      "price": 324.71,
      "change24h": -14.005,
      "volume24h": 5361691.15598,
      "marketCap": 0,
      "imageUrl": "",
      "href": "https://www.binance.com/en/trade/TSLAB_USDT"
    },
    {
      "symbol": "DODOUSDT",
      "base": "DODO",
      "name": "DODO",
      "price": 0.01966,
      "change24h": 4.63,
      "volume24h": 4976589.483488,
      "marketCap": 0,
      "imageUrl": "",
      "href": "https://www.binance.com/en/trade/DODO_USDT"
    },
    {
      "symbol": "GOOGLBUSDT",
      "base": "GOOGLB",
      "name": "GOOGLB",
      "price": 318.8,
      "change24h": -8.459,
      "volume24h": 4975984.75363,
      "marketCap": 0,
      "imageUrl": "",
      "href": "https://www.binance.com/en/trade/GOOGLB_USDT"
    },
    {
      "symbol": "BARDUSDT",
      "base": "BARD",
      "name": "BARD",
      "price": 0.1326,
      "change24h": 6.592,
      "volume24h": 4962230.77733,
      "marketCap": 0,
      "imageUrl": "",
      "href": "https://www.binance.com/en/trade/BARD_USDT"
    },
    {
      "symbol": "SOXLBUSDT",
      "base": "SOXLB",
      "name": "SOXLB",
      "price": 156.96,
      "change24h": -1.753,
      "volume24h": 4864810.72587,
      "marketCap": 0,
      "imageUrl": "",
      "href": "https://www.binance.com/en/trade/SOXLB_USDT"
    },
    {
      "symbol": "ASTERUSDT",
      "base": "ASTER",
      "name": "ASTER",
      "price": 0.624,
      "change24h": -0.319,
      "volume24h": 4740674.9679,
      "marketCap": 0,
      "imageUrl": "",
      "href": "https://www.binance.com/en/trade/ASTER_USDT"
    },
    {
      "symbol": "FILUSDT",
      "base": "FIL",
      "name": "FIL",
      "price": 0.7303,
      "change24h": -4.76,
      "volume24h": 4683970.049132,
      "marketCap": 0,
      "imageUrl": "",
      "href": "https://www.binance.com/en/trade/FIL_USDT"
    },
    {
      "symbol": "ALLOUSDT",
      "base": "ALLO",
      "name": "ALLO",
      "price": 0.5055,
      "change24h": 0.838,
      "volume24h": 4582492.9881,
      "marketCap": 0,
      "imageUrl": "",
      "href": "https://www.binance.com/en/trade/ALLO_USDT"
    },
    {
      "symbol": "MORPHOUSDT",
      "base": "MORPHO",
      "name": "MORPHO",
      "price": 1.951,
      "change24h": -0.611,
      "volume24h": 4367145.64055,
      "marketCap": 0,
      "imageUrl": "",
      "href": "https://www.binance.com/en/trade/MORPHO_USDT"
    },
    {
      "symbol": "SKHYBUSDT",
      "base": "SKHYB",
      "name": "SKHYB",
      "price": 172.49,
      "change24h": 3.542,
      "volume24h": 4366636.85304,
      "marketCap": 0,
      "imageUrl": "",
      "href": "https://www.binance.com/en/trade/SKHYB_USDT"
    },
    {
      "symbol": "KORUBUSDT",
      "base": "KORUB",
      "name": "KORUB",
      "price": 21.55,
      "change24h": 3.457,
      "volume24h": 4323936.4033,
      "marketCap": 0,
      "imageUrl": "",
      "href": "https://www.binance.com/en/trade/KORUB_USDT"
    },
    {
      "symbol": "VIRTUALUSDT",
      "base": "VIRTUAL",
      "name": "VIRTUAL",
      "price": 0.6126,
      "change24h": -5.565,
      "volume24h": 4167080.03074,
      "marketCap": 0,
      "imageUrl": "",
      "href": "https://www.binance.com/en/trade/VIRTUAL_USDT"
    },
    {
      "symbol": "XUSDUSDT",
      "base": "XUSD",
      "name": "XUSD",
      "price": 1.0009,
      "change24h": -0.01,
      "volume24h": 4042077.2207,
      "marketCap": 0,
      "imageUrl": "",
      "href": "https://www.binance.com/en/trade/XUSD_USDT"
    },
    {
      "symbol": "ARBUSDT",
      "base": "ARB",
      "name": "ARB",
      "price": 0.0864,
      "change24h": -4.53,
      "volume24h": 3937677.92774,
      "marketCap": 0,
      "imageUrl": "",
      "href": "https://www.binance.com/en/trade/ARB_USDT"
    },
    {
      "symbol": "ZKCUSDT",
      "base": "ZKC",
      "name": "ZKC",
      "price": 0.0438,
      "change24h": 4.038,
      "volume24h": 3880612.36624,
      "marketCap": 0,
      "imageUrl": "",
      "href": "https://www.binance.com/en/trade/ZKC_USDT"
    },
    {
      "symbol": "TLMUSDT",
      "base": "TLM",
      "name": "TLM",
      "price": 0.001827,
      "change24h": -3.588,
      "volume24h": 3834954.017945,
      "marketCap": 0,
      "imageUrl": "",
      "href": "https://www.binance.com/en/trade/TLM_USDT"
    },
    {
      "symbol": "NFPUSDT",
      "base": "NFP",
      "name": "NFP",
      "price": 0.00181,
      "change24h": -66.168,
      "volume24h": 3834002.83185,
      "marketCap": 0,
      "imageUrl": "",
      "href": "https://www.binance.com/en/trade/NFP_USDT"
    },
    {
      "symbol": "JTOUSDT",
      "base": "JTO",
      "name": "JTO",
      "price": 0.6481,
      "change24h": 2.208,
      "volume24h": 3813354.45891,
      "marketCap": 0,
      "imageUrl": "",
      "href": "https://www.binance.com/en/trade/JTO_USDT"
    },
    {
      "symbol": "PENGUUSDT",
      "base": "PENGU",
      "name": "PENGU",
      "price": 0.006127,
      "change24h": -2.653,
      "volume24h": 3811604.047117,
      "marketCap": 0,
      "imageUrl": "",
      "href": "https://www.binance.com/en/trade/PENGU_USDT"
    },
    {
      "symbol": "KGSTUSDT",
      "base": "KGST",
      "name": "KGST",
      "price": 0.011444,
      "change24h": -0.009,
      "volume24h": 3808078.083593,
      "marketCap": 0,
      "imageUrl": "",
      "href": "https://www.binance.com/en/trade/KGST_USDT"
    },
    {
      "symbol": "NIGHTUSDT",
      "base": "NIGHT",
      "name": "NIGHT",
      "price": 0.02106,
      "change24h": -0.095,
      "volume24h": 3740579.62459,
      "marketCap": 0,
      "imageUrl": "",
      "href": "https://www.binance.com/en/trade/NIGHT_USDT"
    },
    {
      "symbol": "XPLUSDT",
      "base": "XPL",
      "name": "XPL",
      "price": 0.08224,
      "change24h": -2.663,
      "volume24h": 3597347.004819,
      "marketCap": 0,
      "imageUrl": "",
      "href": "https://www.binance.com/en/trade/XPL_USDT"
    },
    {
      "symbol": "BCHUSDT",
      "base": "BCH",
      "name": "BCH",
      "price": 214.5,
      "change24h": -2.633,
      "volume24h": 3548479.8906,
      "marketCap": 0,
      "imageUrl": "",
      "href": "https://www.binance.com/en/trade/BCH_USDT"
    },
    {
      "symbol": "APTUSDT",
      "base": "APT",
      "name": "APT",
      "price": 0.618,
      "change24h": 1.311,
      "volume24h": 3547376.59896,
      "marketCap": 0,
      "imageUrl": "",
      "href": "https://www.binance.com/en/trade/APT_USDT"
    },
    {
      "symbol": "DOTUSDT",
      "base": "DOT",
      "name": "DOT",
      "price": 0.816,
      "change24h": -2.741,
      "volume24h": 3528354.27497,
      "marketCap": 0,
      "imageUrl": "",
      "href": "https://www.binance.com/en/trade/DOT_USDT"
    },
    {
      "symbol": "FETUSDT",
      "base": "FET",
      "name": "FET",
      "price": 0.153,
      "change24h": -1.29,
      "volume24h": 3449715.47042,
      "marketCap": 0,
      "imageUrl": "",
      "href": "https://www.binance.com/en/trade/FET_USDT"
    },
    {
      "symbol": "INJUSDT",
      "base": "INJ",
      "name": "INJ",
      "price": 5.157,
      "change24h": -1.169,
      "volume24h": 3319084.55139,
      "marketCap": 0,
      "imageUrl": "",
      "href": "https://www.binance.com/en/trade/INJ_USDT"
    },
    {
      "symbol": "DASHUSDT",
      "base": "DASH",
      "name": "DASH",
      "price": 33.4,
      "change24h": -0.477,
      "volume24h": 3092012.19202,
      "marketCap": 0,
      "imageUrl": "",
      "href": "https://www.binance.com/en/trade/DASH_USDT"
    },
    {
      "symbol": "LDOUSDT",
      "base": "LDO",
      "name": "LDO",
      "price": 0.3918,
      "change24h": -1.657,
      "volume24h": 2985448.208607,
      "marketCap": 0,
      "imageUrl": "",
      "href": "https://www.binance.com/en/trade/LDO_USDT"
    },
    {
      "symbol": "LRCUSDT",
      "base": "LRC",
      "name": "LRC",
      "price": 0.01879,
      "change24h": -6.238,
      "volume24h": 2891184.21049,
      "marketCap": 0,
      "imageUrl": "",
      "href": "https://www.binance.com/en/trade/LRC_USDT"
    },
    {
      "symbol": "HOMEUSDT",
      "base": "HOME",
      "name": "HOME",
      "price": 0.00614,
      "change24h": -7.808,
      "volume24h": 2768364.20398,
      "marketCap": 0,
      "imageUrl": "",
      "href": "https://www.binance.com/en/trade/HOME_USDT"
    },
    {
      "symbol": "EPICUSDT",
      "base": "EPIC",
      "name": "EPIC",
      "price": 0.6506,
      "change24h": 9.824,
      "volume24h": 2711246.72997,
      "marketCap": 0,
      "imageUrl": "",
      "href": "https://www.binance.com/en/trade/EPIC_USDT"
    },
    {
      "symbol": "SNXUSDT",
      "base": "SNX",
      "name": "SNX",
      "price": 0.225,
      "change24h": -1.316,
      "volume24h": 2691177.7112,
      "marketCap": 0,
      "imageUrl": "",
      "href": "https://www.binance.com/en/trade/SNX_USDT"
    },
    {
      "symbol": "BONKUSDT",
      "base": "BONK",
      "name": "BONK",
      "price": 0.00000295,
      "change24h": -4.221,
      "volume24h": 2624890.46135981,
      "marketCap": 0,
      "imageUrl": "",
      "href": "https://www.binance.com/en/trade/BONK_USDT"
    },
    {
      "symbol": "ETHFIUSDT",
      "base": "ETHFI",
      "name": "ETHFI",
      "price": 0.4572,
      "change24h": -3.768,
      "volume24h": 2493933.57395,
      "marketCap": 0,
      "imageUrl": "",
      "href": "https://www.binance.com/en/trade/ETHFI_USDT"
    },
    {
      "symbol": "POLUSDT",
      "base": "POL",
      "name": "POL",
      "price": 0.07761,
      "change24h": -1.672,
      "volume24h": 2483236.379829,
      "marketCap": 0,
      "imageUrl": "",
      "href": "https://www.binance.com/en/trade/POL_USDT"
    },
    {
      "symbol": "ACEUSDT",
      "base": "ACE",
      "name": "ACE",
      "price": 0.0818,
      "change24h": -9.01,
      "volume24h": 2463943.50665,
      "marketCap": 0,
      "imageUrl": "",
      "href": "https://www.binance.com/en/trade/ACE_USDT"
    },
    {
      "symbol": "LAUSDT",
      "base": "LA",
      "name": "LA",
      "price": 0.058,
      "change24h": 8.007,
      "volume24h": 2434798.5265,
      "marketCap": 0,
      "imageUrl": "",
      "href": "https://www.binance.com/en/trade/LA_USDT"
    },
    {
      "symbol": "ZILUSDT",
      "base": "ZIL",
      "name": "ZIL",
      "price": 0.002506,
      "change24h": 3,
      "volume24h": 2387336.7207193,
      "marketCap": 0,
      "imageUrl": "",
      "href": "https://www.binance.com/en/trade/ZIL_USDT"
    },
    {
      "symbol": "HEMIUSDT",
      "base": "HEMI",
      "name": "HEMI",
      "price": 0.00528,
      "change24h": 3.529,
      "volume24h": 2364568.793601,
      "marketCap": 0,
      "imageUrl": "",
      "href": "https://www.binance.com/en/trade/HEMI_USDT"
    },
    {
      "symbol": "JSTUSDT",
      "base": "JST",
      "name": "JST",
      "price": 0.10003,
      "change24h": -0.902,
      "volume24h": 2293889.190144,
      "marketCap": 0,
      "imageUrl": "",
      "href": "https://www.binance.com/en/trade/JST_USDT"
    },
    {
      "symbol": "SAPIENUSDT",
      "base": "SAPIEN",
      "name": "SAPIEN",
      "price": 0.0798,
      "change24h": 1.269,
      "volume24h": 2244863.06377,
      "marketCap": 0,
      "imageUrl": "",
      "href": "https://www.binance.com/en/trade/SAPIEN_USDT"
    },
    {
      "symbol": "SHIBUSDT",
      "base": "SHIB",
      "name": "SHIB",
      "price": 0.00000415,
      "change24h": -2.123,
      "volume24h": 2173711.90468123,
      "marketCap": 0,
      "imageUrl": "",
      "href": "https://www.binance.com/en/trade/SHIB_USDT"
    },
    {
      "symbol": "ICPUSDT",
      "base": "ICP",
      "name": "ICP",
      "price": 2.158,
      "change24h": -1.506,
      "volume24h": 2156337.3199,
      "marketCap": 0,
      "imageUrl": "",
      "href": "https://www.binance.com/en/trade/ICP_USDT"
    }
  ]
}
