{
  "updatedAt": "2026-07-23T19:45:31.487Z",
  "source": "binance",
  "pollMs": 5000,
  "rows": [
    {
      "symbol": "USDCUSDT",
      "base": "USDC",
      "name": "USDC",
      "price": 1.00074,
      "change24h": 0.024,
      "volume24h": 1913143605.43625,
      "marketCap": 0,
      "imageUrl": "",
      "href": "https://www.binance.com/en/trade/USDC_USDT"
    },
    {
      "symbol": "BTCUSDT",
      "base": "BTC",
      "name": "BTC",
      "price": 64754.01,
      "change24h": -1.706,
      "volume24h": 929426079.292948,
      "marketCap": 0,
      "imageUrl": "",
      "href": "https://www.binance.com/en/trade/BTC_USDT"
    },
    {
      "symbol": "ETHUSDT",
      "base": "ETH",
      "name": "ETH",
      "price": 1875.15,
      "change24h": -2.632,
      "volume24h": 421504920.089391,
      "marketCap": 0,
      "imageUrl": "",
      "href": "https://www.binance.com/en/trade/ETH_USDT"
    },
    {
      "symbol": "AEROUSDT",
      "base": "AERO",
      "name": "AERO",
      "price": 0.4241,
      "change24h": -3.129,
      "volume24h": 204800430.33004,
      "marketCap": 0,
      "imageUrl": "",
      "href": "https://www.binance.com/en/trade/AERO_USDT"
    },
    {
      "symbol": "KITEUSDT",
      "base": "KITE",
      "name": "KITE",
      "price": 0.1131,
      "change24h": -6.297,
      "volume24h": 201221595.93786,
      "marketCap": 0,
      "imageUrl": "",
      "href": "https://www.binance.com/en/trade/KITE_USDT"
    },
    {
      "symbol": "USD1USDT",
      "base": "USD1",
      "name": "USD1",
      "price": 0.99973,
      "change24h": 0,
      "volume24h": 122646929.39006,
      "marketCap": 0,
      "imageUrl": "",
      "href": "https://www.binance.com/en/trade/USD1_USDT"
    },
    {
      "symbol": "SOLUSDT",
      "base": "SOL",
      "name": "SOL",
      "price": 75.6,
      "change24h": -2.527,
      "volume24h": 102294666.41932,
      "marketCap": 0,
      "imageUrl": "",
      "href": "https://www.binance.com/en/trade/SOL_USDT"
    },
    {
      "symbol": "DOGEUSDT",
      "base": "DOGE",
      "name": "DOGE",
      "price": 0.06924,
      "change24h": -4.51,
      "volume24h": 59148438.77937,
      "marketCap": 0,
      "imageUrl": "",
      "href": "https://www.binance.com/en/trade/DOGE_USDT"
    },
    {
      "symbol": "BANKUSDT",
      "base": "BANK",
      "name": "BANK",
      "price": 0.2516,
      "change24h": 10.206,
      "volume24h": 58649765.57195,
      "marketCap": 0,
      "imageUrl": "",
      "href": "https://www.binance.com/en/trade/BANK_USDT"
    },
    {
      "symbol": "XRPUSDT",
      "base": "XRP",
      "name": "XRP",
      "price": 1.1044,
      "change24h": -2.978,
      "volume24h": 56886454.40711,
      "marketCap": 0,
      "imageUrl": "",
      "href": "https://www.binance.com/en/trade/XRP_USDT"
    },
    {
      "symbol": "ZECUSDT",
      "base": "ZEC",
      "name": "ZEC",
      "price": 503.13,
      "change24h": -1.503,
      "volume24h": 45123886.47928,
      "marketCap": 0,
      "imageUrl": "",
      "href": "https://www.binance.com/en/trade/ZEC_USDT"
    },
    {
      "symbol": "DEXEUSDT",
      "base": "DEXE",
      "name": "DEXE",
      "price": 2.181,
      "change24h": -51.436,
      "volume24h": 43210364.84288,
      "marketCap": 0,
      "imageUrl": "",
      "href": "https://www.binance.com/en/trade/DEXE_USDT"
    },
    {
      "symbol": "BNBUSDT",
      "base": "BNB",
      "name": "BNB",
      "price": 566.21,
      "change24h": -0.621,
      "volume24h": 40033015.87075,
      "marketCap": 0,
      "imageUrl": "",
      "href": "https://www.binance.com/en/trade/BNB_USDT"
    },
    {
      "symbol": "WLFIUSDT",
      "base": "WLFI",
      "name": "WLFI",
      "price": 0.0597,
      "change24h": 6.417,
      "volume24h": 31068007.05695,
      "marketCap": 0,
      "imageUrl": "",
      "href": "https://www.binance.com/en/trade/WLFI_USDT"
    },
    {
      "symbol": "ZAMAUSDT",
      "base": "ZAMA",
      "name": "ZAMA",
      "price": 0.05436,
      "change24h": 24.65,
      "volume24h": 30049179.79939,
      "marketCap": 0,
      "imageUrl": "",
      "href": "https://www.binance.com/en/trade/ZAMA_USDT"
    },
    {
      "symbol": "OPNUSDT",
      "base": "OPN",
      "name": "OPN",
      "price": 0.067,
      "change24h": -2.758,
      "volume24h": 25754091.02977,
      "marketCap": 0,
      "imageUrl": "",
      "href": "https://www.binance.com/en/trade/OPN_USDT"
    },
    {
      "symbol": "RLUSDUSDT",
      "base": "RLUSD",
      "name": "RLUSD",
      "price": 1.0008,
      "change24h": 0.02,
      "volume24h": 25166295.7292,
      "marketCap": 0,
      "imageUrl": "",
      "href": "https://www.binance.com/en/trade/RLUSD_USDT"
    },
    {
      "symbol": "SPCXBUSDT",
      "base": "SPCXB",
      "name": "SPCXB",
      "price": 116.73,
      "change24h": 0.499,
      "volume24h": 24725882.16339,
      "marketCap": 0,
      "imageUrl": "",
      "href": "https://www.binance.com/en/trade/SPCXB_USDT"
    },
    {
      "symbol": "FDUSDUSDT",
      "base": "FDUSD",
      "name": "FDUSD",
      "price": 0.9982,
      "change24h": 0,
      "volume24h": 24192461.3833,
      "marketCap": 0,
      "imageUrl": "",
      "href": "https://www.binance.com/en/trade/FDUSD_USDT"
    },
    {
      "symbol": "EURUSDT",
      "base": "EUR",
      "name": "EUR",
      "price": 1.1384,
      "change24h": -0.289,
      "volume24h": 22732875.57511,
      "marketCap": 0,
      "imageUrl": "",
      "href": "https://www.binance.com/en/trade/EUR_USDT"
    },
    {
      "symbol": "TRXUSDT",
      "base": "TRX",
      "name": "TRX",
      "price": 0.3272,
      "change24h": -0.426,
      "volume24h": 21903657.10996,
      "marketCap": 0,
      "imageUrl": "",
      "href": "https://www.binance.com/en/trade/TRX_USDT"
    },
    {
      "symbol": "SNDKBUSDT",
      "base": "SNDKB",
      "name": "SNDKB",
      "price": 1608.33,
      "change24h": 0.441,
      "volume24h": 20687730.411635,
      "marketCap": 0,
      "imageUrl": "",
      "href": "https://www.binance.com/en/trade/SNDKB_USDT"
    },
    {
      "symbol": "RIFUSDT",
      "base": "RIF",
      "name": "RIF",
      "price": 0.102,
      "change24h": 59.875,
      "volume24h": 17677095.6123,
      "marketCap": 0,
      "imageUrl": "",
      "href": "https://www.binance.com/en/trade/RIF_USDT"
    },
    {
      "symbol": "XAUTUSDT",
      "base": "XAUT",
      "name": "XAUT",
      "price": 4046.51,
      "change24h": -2.005,
      "volume24h": 17675717.699684,
      "marketCap": 0,
      "imageUrl": "",
      "href": "https://www.binance.com/en/trade/XAUT_USDT"
    },
    {
      "symbol": "ENAUSDT",
      "base": "ENA",
      "name": "ENA",
      "price": 0.0883,
      "change24h": -4.952,
      "volume24h": 17649158.51669,
      "marketCap": 0,
      "imageUrl": "",
      "href": "https://www.binance.com/en/trade/ENA_USDT"
    },
    {
      "symbol": "REUSDT",
      "base": "RE",
      "name": "RE",
      "price": 0.5235,
      "change24h": 6.424,
      "volume24h": 17375998.94789,
      "marketCap": 0,
      "imageUrl": "",
      "href": "https://www.binance.com/en/trade/RE_USDT"
    },
    {
      "symbol": "UUSDT",
      "base": "U",
      "name": "U",
      "price": 1.0006,
      "change24h": 0.04,
      "volume24h": 16852011.9873,
      "marketCap": 0,
      "imageUrl": "",
      "href": "https://www.binance.com/en/trade/U_USDT"
    },
    {
      "symbol": "VANAUSDT",
      "base": "VANA",
      "name": "VANA",
      "price": 1.231,
      "change24h": 0.326,
      "volume24h": 15421937.11609,
      "marketCap": 0,
      "imageUrl": "",
      "href": "https://www.binance.com/en/trade/VANA_USDT"
    },
    {
      "symbol": "WLDUSDT",
      "base": "WLD",
      "name": "WLD",
      "price": 0.3795,
      "change24h": -3.213,
      "volume24h": 14868078.24386,
      "marketCap": 0,
      "imageUrl": "",
      "href": "https://www.binance.com/en/trade/WLD_USDT"
    },
    {
      "symbol": "SUIUSDT",
      "base": "SUI",
      "name": "SUI",
      "price": 0.7446,
      "change24h": -2.73,
      "volume24h": 14682247.20884,
      "marketCap": 0,
      "imageUrl": "",
      "href": "https://www.binance.com/en/trade/SUI_USDT"
    },
    {
      "symbol": "LTCUSDT",
      "base": "LTC",
      "name": "LTC",
      "price": 46.89,
      "change24h": -0.615,
      "volume24h": 14280818.74528,
      "marketCap": 0,
      "imageUrl": "",
      "href": "https://www.binance.com/en/trade/LTC_USDT"
    },
    {
      "symbol": "ONDOUSDT",
      "base": "ONDO",
      "name": "ONDO",
      "price": 0.3997,
      "change24h": -3.056,
      "volume24h": 13576002.50014,
      "marketCap": 0,
      "imageUrl": "",
      "href": "https://www.binance.com/en/trade/ONDO_USDT"
    },
    {
      "symbol": "ADAUSDT",
      "base": "ADA",
      "name": "ADA",
      "price": 0.1691,
      "change24h": -3.15,
      "volume24h": 11972552.65689,
      "marketCap": 0,
      "imageUrl": "",
      "href": "https://www.binance.com/en/trade/ADA_USDT"
    },
    {
      "symbol": "NEARUSDT",
      "base": "NEAR",
      "name": "NEAR",
      "price": 1.882,
      "change24h": 1.074,
      "volume24h": 11938038.4121,
      "marketCap": 0,
      "imageUrl": "",
      "href": "https://www.binance.com/en/trade/NEAR_USDT"
    },
    {
      "symbol": "PAXGUSDT",
      "base": "PAXG",
      "name": "PAXG",
      "price": 4043.82,
      "change24h": -2.056,
      "volume24h": 11796920.385256,
      "marketCap": 0,
      "imageUrl": "",
      "href": "https://www.binance.com/en/trade/PAXG_USDT"
    },
    {
      "symbol": "SYNUSDT",
      "base": "SYN",
      "name": "SYN",
      "price": 0.14967,
      "change24h": -18.525,
      "volume24h": 11643828.547159,
      "marketCap": 0,
      "imageUrl": "",
      "href": "https://www.binance.com/en/trade/SYN_USDT"
    },
    {
      "symbol": "KAITOUSDT",
      "base": "KAITO",
      "name": "KAITO",
      "price": 1.0473,
      "change24h": 6.595,
      "volume24h": 11240576.22964,
      "marketCap": 0,
      "imageUrl": "",
      "href": "https://www.binance.com/en/trade/KAITO_USDT"
    },
    {
      "symbol": "XLMUSDT",
      "base": "XLM",
      "name": "XLM",
      "price": 0.1827,
      "change24h": -2.56,
      "volume24h": 10821754.3973,
      "marketCap": 0,
      "imageUrl": "",
      "href": "https://www.binance.com/en/trade/XLM_USDT"
    },
    {
      "symbol": "PEPEUSDT",
      "base": "PEPE",
      "name": "PEPE",
      "price": 0.00000277,
      "change24h": -3.147,
      "volume24h": 10754741.38031987,
      "marketCap": 0,
      "imageUrl": "",
      "href": "https://www.binance.com/en/trade/PEPE_USDT"
    },
    {
      "symbol": "UNIUSDT",
      "base": "UNI",
      "name": "UNI",
      "price": 3.776,
      "change24h": -1.667,
      "volume24h": 10272524.13513,
      "marketCap": 0,
      "imageUrl": "",
      "href": "https://www.binance.com/en/trade/UNI_USDT"
    },
    {
      "symbol": "AVAXUSDT",
      "base": "AVAX",
      "name": "AVAX",
      "price": 6.271,
      "change24h": -4.913,
      "volume24h": 10228349.12035,
      "marketCap": 0,
      "imageUrl": "",
      "href": "https://www.binance.com/en/trade/AVAX_USDT"
    },
    {
      "symbol": "UTKUSDT",
      "base": "UTK",
      "name": "UTK",
      "price": 0.00795,
      "change24h": 16.228,
      "volume24h": 10207948.62723,
      "marketCap": 0,
      "imageUrl": "",
      "href": "https://www.binance.com/en/trade/UTK_USDT"
    },
    {
      "symbol": "AAVEUSDT",
      "base": "AAVE",
      "name": "AAVE",
      "price": 95.33,
      "change24h": -2.744,
      "volume24h": 9647186.40539,
      "marketCap": 0,
      "imageUrl": "",
      "href": "https://www.binance.com/en/trade/AAVE_USDT"
    },
    {
      "symbol": "ERAUSDT",
      "base": "ERA",
      "name": "ERA",
      "price": 0.0956,
      "change24h": 0.315,
      "volume24h": 9288383.36497,
      "marketCap": 0,
      "imageUrl": "",
      "href": "https://www.binance.com/en/trade/ERA_USDT"
    },
    {
      "symbol": "LINKUSDT",
      "base": "LINK",
      "name": "LINK",
      "price": 8.455,
      "change24h": -1.834,
      "volume24h": 9081582.98613,
      "marketCap": 0,
      "imageUrl": "",
      "href": "https://www.binance.com/en/trade/LINK_USDT"
    },
    {
      "symbol": "HBARUSDT",
      "base": "HBAR",
      "name": "HBAR",
      "price": 0.0721,
      "change24h": 0.39,
      "volume24h": 8575466.91499,
      "marketCap": 0,
      "imageUrl": "",
      "href": "https://www.binance.com/en/trade/HBAR_USDT"
    },
    {
      "symbol": "TRUMPUSDT",
      "base": "TRUMP",
      "name": "TRUMP",
      "price": 1.613,
      "change24h": 0.124,
      "volume24h": 8275412.342542,
      "marketCap": 0,
      "imageUrl": "",
      "href": "https://www.binance.com/en/trade/TRUMP_USDT"
    },
    {
      "symbol": "TAOUSDT",
      "base": "TAO",
      "name": "TAO",
      "price": 193.1,
      "change24h": -1.93,
      "volume24h": 7807432.76173,
      "marketCap": 0,
      "imageUrl": "",
      "href": "https://www.binance.com/en/trade/TAO_USDT"
    },
    {
      "symbol": "TONUSDT",
      "base": "TON",
      "name": "TON",
      "price": 1.6,
      "change24h": 0.946,
      "volume24h": 7717352.41982,
      "marketCap": 0,
      "imageUrl": "",
      "href": "https://www.binance.com/en/trade/TON_USDT"
    },
    {
      "symbol": "MUBUSDT",
      "base": "MUB",
      "name": "MUB",
      "price": 981.54,
      "change24h": 0.803,
      "volume24h": 7695237.07483,
      "marketCap": 0,
      "imageUrl": "",
      "href": "https://www.binance.com/en/trade/MUB_USDT"
    },
    {
      "symbol": "TSLABUSDT",
      "base": "TSLAB",
      "name": "TSLAB",
      "price": 317.04,
      "change24h": -15.537,
      "volume24h": 7585695.44704,
      "marketCap": 0,
      "imageUrl": "",
      "href": "https://www.binance.com/en/trade/TSLAB_USDT"
    },
    {
      "symbol": "GRAMUSDT",
      "base": "GRAM",
      "name": "GRAM",
      "price": 1.458,
      "change24h": -3.187,
      "volume24h": 7568286.59304,
      "marketCap": 0,
      "imageUrl": "",
      "href": "https://www.binance.com/en/trade/GRAM_USDT"
    },
    {
      "symbol": "币安人生USDT",
      "base": "币安人生",
      "name": "币安人生",
      "price": 0.6945,
      "change24h": 15.692,
      "volume24h": 7008953.78693,
      "marketCap": 0,
      "imageUrl": "",
      "href": "https://www.binance.com/en/trade/币安人生_USDT"
    },
    {
      "symbol": "CRCLBUSDT",
      "base": "CRCLB",
      "name": "CRCLB",
      "price": 62.36,
      "change24h": -5.011,
      "volume24h": 6790115.7809,
      "marketCap": 0,
      "imageUrl": "",
      "href": "https://www.binance.com/en/trade/CRCLB_USDT"
    },
    {
      "symbol": "LAUSDT",
      "base": "LA",
      "name": "LA",
      "price": 0.0698,
      "change24h": 29.02,
      "volume24h": 6060755.91483,
      "marketCap": 0,
      "imageUrl": "",
      "href": "https://www.binance.com/en/trade/LA_USDT"
    },
    {
      "symbol": "BARDUSDT",
      "base": "BARD",
      "name": "BARD",
      "price": 0.1281,
      "change24h": 2.316,
      "volume24h": 5444306.92102,
      "marketCap": 0,
      "imageUrl": "",
      "href": "https://www.binance.com/en/trade/BARD_USDT"
    },
    {
      "symbol": "GOOGLBUSDT",
      "base": "GOOGLB",
      "name": "GOOGLB",
      "price": 318.5,
      "change24h": -7.857,
      "volume24h": 5342050.95584,
      "marketCap": 0,
      "imageUrl": "",
      "href": "https://www.binance.com/en/trade/GOOGLB_USDT"
    },
    {
      "symbol": "PUMPUSDT",
      "base": "PUMP",
      "name": "PUMP",
      "price": 0.001896,
      "change24h": 1.12,
      "volume24h": 5117968.473896,
      "marketCap": 0,
      "imageUrl": "",
      "href": "https://www.binance.com/en/trade/PUMP_USDT"
    },
    {
      "symbol": "FILUSDT",
      "base": "FIL",
      "name": "FIL",
      "price": 0.7263,
      "change24h": -4.822,
      "volume24h": 4972419.049083,
      "marketCap": 0,
      "imageUrl": "",
      "href": "https://www.binance.com/en/trade/FIL_USDT"
    },
    {
      "symbol": "ASTERUSDT",
      "base": "ASTER",
      "name": "ASTER",
      "price": 0.621,
      "change24h": -0.481,
      "volume24h": 4772620.87313,
      "marketCap": 0,
      "imageUrl": "",
      "href": "https://www.binance.com/en/trade/ASTER_USDT"
    },
    {
      "symbol": "SOXLBUSDT",
      "base": "SOXLB",
      "name": "SOXLB",
      "price": 153.03,
      "change24h": -5.903,
      "volume24h": 4577209.08144,
      "marketCap": 0,
      "imageUrl": "",
      "href": "https://www.binance.com/en/trade/SOXLB_USDT"
    },
    {
      "symbol": "BCHUSDT",
      "base": "BCH",
      "name": "BCH",
      "price": 209.6,
      "change24h": -4.51,
      "volume24h": 4439745.1384,
      "marketCap": 0,
      "imageUrl": "",
      "href": "https://www.binance.com/en/trade/BCH_USDT"
    },
    {
      "symbol": "SKHYBUSDT",
      "base": "SKHYB",
      "name": "SKHYB",
      "price": 168.76,
      "change24h": 1.066,
      "volume24h": 4395232.0567,
      "marketCap": 0,
      "imageUrl": "",
      "href": "https://www.binance.com/en/trade/SKHYB_USDT"
    },
    {
      "symbol": "ALLOUSDT",
      "base": "ALLO",
      "name": "ALLO",
      "price": 0.5113,
      "change24h": 1.853,
      "volume24h": 4389577.32482,
      "marketCap": 0,
      "imageUrl": "",
      "href": "https://www.binance.com/en/trade/ALLO_USDT"
    },
    {
      "symbol": "KORUBUSDT",
      "base": "KORUB",
      "name": "KORUB",
      "price": 21.48,
      "change24h": 3.319,
      "volume24h": 4367783.3276,
      "marketCap": 0,
      "imageUrl": "",
      "href": "https://www.binance.com/en/trade/KORUB_USDT"
    },
    {
      "symbol": "XUSDUSDT",
      "base": "XUSD",
      "name": "XUSD",
      "price": 1.0011,
      "change24h": 0.02,
      "volume24h": 4352408.7139,
      "marketCap": 0,
      "imageUrl": "",
      "href": "https://www.binance.com/en/trade/XUSD_USDT"
    },
    {
      "symbol": "JTOUSDT",
      "base": "JTO",
      "name": "JTO",
      "price": 0.6348,
      "change24h": 2.918,
      "volume24h": 4203261.32139,
      "marketCap": 0,
      "imageUrl": "",
      "href": "https://www.binance.com/en/trade/JTO_USDT"
    },
    {
      "symbol": "ZKCUSDT",
      "base": "ZKC",
      "name": "ZKC",
      "price": 0.0441,
      "change24h": 3.279,
      "volume24h": 4104777.17213,
      "marketCap": 0,
      "imageUrl": "",
      "href": "https://www.binance.com/en/trade/ZKC_USDT"
    },
    {
      "symbol": "DODOUSDT",
      "base": "DODO",
      "name": "DODO",
      "price": 0.01982,
      "change24h": 4.042,
      "volume24h": 3987912.864806,
      "marketCap": 0,
      "imageUrl": "",
      "href": "https://www.binance.com/en/trade/DODO_USDT"
    },
    {
      "symbol": "ARBUSDT",
      "base": "ARB",
      "name": "ARB",
      "price": 0.0864,
      "change24h": -4.319,
      "volume24h": 3957824.31038,
      "marketCap": 0,
      "imageUrl": "",
      "href": "https://www.binance.com/en/trade/ARB_USDT"
    },
    {
      "symbol": "NFPUSDT",
      "base": "NFP",
      "name": "NFP",
      "price": 0.00181,
      "change24h": -66.168,
      "volume24h": 3834002.83185,
      "marketCap": 0,
      "imageUrl": "",
      "href": "https://www.binance.com/en/trade/NFP_USDT"
    },
    {
      "symbol": "MIRAUSDT",
      "base": "MIRA",
      "name": "MIRA",
      "price": 0.0458,
      "change24h": -4.583,
      "volume24h": 3687215.50537,
      "marketCap": 0,
      "imageUrl": "",
      "href": "https://www.binance.com/en/trade/MIRA_USDT"
    },
    {
      "symbol": "VIRTUALUSDT",
      "base": "VIRTUAL",
      "name": "VIRTUAL",
      "price": 0.6104,
      "change24h": -3.418,
      "volume24h": 3613345.23485,
      "marketCap": 0,
      "imageUrl": "",
      "href": "https://www.binance.com/en/trade/VIRTUAL_USDT"
    },
    {
      "symbol": "PENGUUSDT",
      "base": "PENGU",
      "name": "PENGU",
      "price": 0.006038,
      "change24h": -4.113,
      "volume24h": 3588768.355374,
      "marketCap": 0,
      "imageUrl": "",
      "href": "https://www.binance.com/en/trade/PENGU_USDT"
    },
    {
      "symbol": "FETUSDT",
      "base": "FET",
      "name": "FET",
      "price": 0.1518,
      "change24h": -2.065,
      "volume24h": 3508030.18088,
      "marketCap": 0,
      "imageUrl": "",
      "href": "https://www.binance.com/en/trade/FET_USDT"
    },
    {
      "symbol": "NIGHTUSDT",
      "base": "NIGHT",
      "name": "NIGHT",
      "price": 0.02143,
      "change24h": 6.037,
      "volume24h": 3488519.41035,
      "marketCap": 0,
      "imageUrl": "",
      "href": "https://www.binance.com/en/trade/NIGHT_USDT"
    },
    {
      "symbol": "KGSTUSDT",
      "base": "KGST",
      "name": "KGST",
      "price": 0.011444,
      "change24h": -0.017,
      "volume24h": 3422686.732644,
      "marketCap": 0,
      "imageUrl": "",
      "href": "https://www.binance.com/en/trade/KGST_USDT"
    },
    {
      "symbol": "DOTUSDT",
      "base": "DOT",
      "name": "DOT",
      "price": 0.815,
      "change24h": -3.207,
      "volume24h": 3370796.63036,
      "marketCap": 0,
      "imageUrl": "",
      "href": "https://www.binance.com/en/trade/DOT_USDT"
    },
    {
      "symbol": "TLMUSDT",
      "base": "TLM",
      "name": "TLM",
      "price": 0.001776,
      "change24h": -0.112,
      "volume24h": 3343543.666845,
      "marketCap": 0,
      "imageUrl": "",
      "href": "https://www.binance.com/en/trade/TLM_USDT"
    },
    {
      "symbol": "DASHUSDT",
      "base": "DASH",
      "name": "DASH",
      "price": 32.79,
      "change24h": -2.353,
      "volume24h": 3331395.65525,
      "marketCap": 0,
      "imageUrl": "",
      "href": "https://www.binance.com/en/trade/DASH_USDT"
    },
    {
      "symbol": "XPLUSDT",
      "base": "XPL",
      "name": "XPL",
      "price": 0.08234,
      "change24h": -1.929,
      "volume24h": 3298369.285171,
      "marketCap": 0,
      "imageUrl": "",
      "href": "https://www.binance.com/en/trade/XPL_USDT"
    },
    {
      "symbol": "INJUSDT",
      "base": "INJ",
      "name": "INJ",
      "price": 5.123,
      "change24h": -1.139,
      "volume24h": 3285633.19117,
      "marketCap": 0,
      "imageUrl": "",
      "href": "https://www.binance.com/en/trade/INJ_USDT"
    },
    {
      "symbol": "HOMEUSDT",
      "base": "HOME",
      "name": "HOME",
      "price": 0.00618,
      "change24h": -1.749,
      "volume24h": 3093948.06625,
      "marketCap": 0,
      "imageUrl": "",
      "href": "https://www.binance.com/en/trade/HOME_USDT"
    },
    {
      "symbol": "APTUSDT",
      "base": "APT",
      "name": "APT",
      "price": 0.608,
      "change24h": -2.564,
      "volume24h": 2958386.00735,
      "marketCap": 0,
      "imageUrl": "",
      "href": "https://www.binance.com/en/trade/APT_USDT"
    },
    {
      "symbol": "LRCUSDT",
      "base": "LRC",
      "name": "LRC",
      "price": 0.01879,
      "change24h": -6.238,
      "volume24h": 2891184.21049,
      "marketCap": 0,
      "imageUrl": "",
      "href": "https://www.binance.com/en/trade/LRC_USDT"
    },
    {
      "symbol": "EPICUSDT",
      "base": "EPIC",
      "name": "EPIC",
      "price": 0.6414,
      "change24h": 7.222,
      "volume24h": 2881939.44574,
      "marketCap": 0,
      "imageUrl": "",
      "href": "https://www.binance.com/en/trade/EPIC_USDT"
    },
    {
      "symbol": "LDOUSDT",
      "base": "LDO",
      "name": "LDO",
      "price": 0.385,
      "change24h": -4.229,
      "volume24h": 2788030.972574,
      "marketCap": 0,
      "imageUrl": "",
      "href": "https://www.binance.com/en/trade/LDO_USDT"
    },
    {
      "symbol": "POLUSDT",
      "base": "POL",
      "name": "POL",
      "price": 0.07701,
      "change24h": -2.371,
      "volume24h": 2763657.170094,
      "marketCap": 0,
      "imageUrl": "",
      "href": "https://www.binance.com/en/trade/POL_USDT"
    },
    {
      "symbol": "ACEUSDT",
      "base": "ACE",
      "name": "ACE",
      "price": 0.0811,
      "change24h": -9.183,
      "volume24h": 2581900.45235,
      "marketCap": 0,
      "imageUrl": "",
      "href": "https://www.binance.com/en/trade/ACE_USDT"
    },
    {
      "symbol": "PROMUSDT",
      "base": "PROM",
      "name": "PROM",
      "price": 1.762,
      "change24h": 16.38,
      "volume24h": 2507609.43676,
      "marketCap": 0,
      "imageUrl": "",
      "href": "https://www.binance.com/en/trade/PROM_USDT"
    },
    {
      "symbol": "ZILUSDT",
      "base": "ZIL",
      "name": "ZIL",
      "price": 0.002429,
      "change24h": -0.123,
      "volume24h": 2439377.7719649,
      "marketCap": 0,
      "imageUrl": "",
      "href": "https://www.binance.com/en/trade/ZIL_USDT"
    },
    {
      "symbol": "HEMIUSDT",
      "base": "HEMI",
      "name": "HEMI",
      "price": 0.00476,
      "change24h": -3.644,
      "volume24h": 2425215.723916,
      "marketCap": 0,
      "imageUrl": "",
      "href": "https://www.binance.com/en/trade/HEMI_USDT"
    },
    {
      "symbol": "JSTUSDT",
      "base": "JST",
      "name": "JST",
      "price": 0.10078,
      "change24h": -0.983,
      "volume24h": 2424793.371531,
      "marketCap": 0,
      "imageUrl": "",
      "href": "https://www.binance.com/en/trade/JST_USDT"
    },
    {
      "symbol": "SHIBUSDT",
      "base": "SHIB",
      "name": "SHIB",
      "price": 0.00000412,
      "change24h": -3.059,
      "volume24h": 2342608.44466436,
      "marketCap": 0,
      "imageUrl": "",
      "href": "https://www.binance.com/en/trade/SHIB_USDT"
    },
    {
      "symbol": "EIGENUSDT",
      "base": "EIGEN",
      "name": "EIGEN",
      "price": 0.2246,
      "change24h": -5.392,
      "volume24h": 2295545.134443,
      "marketCap": 0,
      "imageUrl": "",
      "href": "https://www.binance.com/en/trade/EIGEN_USDT"
    },
    {
      "symbol": "NOMUSDT",
      "base": "NOM",
      "name": "NOM",
      "price": 0.00159,
      "change24h": 3.922,
      "volume24h": 2249592.48141,
      "marketCap": 0,
      "imageUrl": "",
      "href": "https://www.binance.com/en/trade/NOM_USDT"
    },
    {
      "symbol": "ICPUSDT",
      "base": "ICP",
      "name": "ICP",
      "price": 2.154,
      "change24h": -2.313,
      "volume24h": 2196588.57399,
      "marketCap": 0,
      "imageUrl": "",
      "href": "https://www.binance.com/en/trade/ICP_USDT"
    },
    {
      "symbol": "ETHFIUSDT",
      "base": "ETHFI",
      "name": "ETHFI",
      "price": 0.4471,
      "change24h": -2.804,
      "volume24h": 2132998.76125,
      "marketCap": 0,
      "imageUrl": "",
      "href": "https://www.binance.com/en/trade/ETHFI_USDT"
    },
    {
      "symbol": "MORPHOUSDT",
      "base": "MORPHO",
      "name": "MORPHO",
      "price": 1.992,
      "change24h": 2.206,
      "volume24h": 2109524.69271,
      "marketCap": 0,
      "imageUrl": "",
      "href": "https://www.binance.com/en/trade/MORPHO_USDT"
    },
    {
      "symbol": "ZBTUSDT",
      "base": "ZBT",
      "name": "ZBT",
      "price": 0.1139,
      "change24h": 10.368,
      "volume24h": 2035300.23387,
      "marketCap": 0,
      "imageUrl": "",
      "href": "https://www.binance.com/en/trade/ZBT_USDT"
    }
  ]
}
